{
  "chunk_id": "s01_e088_c0007",
  "episode_id": "s01_e088",
  "season": 1,
  "episode": 88,
  "part": null,
  "bonus": false,
  "title": "कांग्रेस का ‘Electile Dysfunction’, Protest के अलबेले किरदार और जवानी के झामफाड़ गाने Teen Taal",
  "chunk_index": 7,
  "word_count": 1000,
  "text": "हैं तो यह जिम्मेदारी राज्य सरकारों की है आप सरकार में है इसका यह मतलब नहीं है कि आप जो चाहते हैं वह हो आप सरकार में हैं इसका यह मतलब है कि लोग जो चाहते हैं आप वह करो आपको उसके लिए वहां पर बैठाया है और बताओ कहने कि यह तो बहुत राष्ट्रपति पद जैसी बातें कर रहे हो तुम बाबा लोकतंत्र में प्रोटेस्ट होता है और कॉन्टेक्स्ट आफ प्रोटेस्ट आपको लगता है कि नहीं हो पा रहा हुं करते हैं और फिर से करते हैं ताकि इसमें जो है वह कांटेस्ट की प्रोटेस्ट की नहीं है है तो यह है और जो ताऊ बात कह गया भी बहुत बारिश की प्रोटेस्ट को समझना बहुत जरूरी है कि कौन से पोर्टल ज़मीन है और कौन से दरअसल कांटेस्ट की प्रोटेस्ट जैसे किसान जब न्यूनतम मजदूरी की भूमि अधिग्रहण की बात करने के लिए रोड पर उतरा कि जब आया तो उसकी मंशा यह कांटेस्ट की नहीं है उसको जा करके चुनाव मैदान में वहां पर है कि भई यह करो भैया आपने कभी नहीं लेकिन यह कांटेस्ट कि मेरी फोटो अगर बार इंडिया टुडे और आजतक चैनल पर आती रहेगी जिसमें चार लोग मुझे ना किए हुए हैं तो संभव है कि टिकट मिल जाए एमपी विधायक और राज्य सभा संकट यह है कि यह सारी महत्वाकांक्षाएं उनको रोड पर की तरह शरीर की तरह मृत्यु करा रहे हैं लेकिन इस दौरान जब यह सब कुछ हो रहा है उत्तर प्रदेश की विधानसभा की कांग्रेस विधान परिषद में भी शून्य पर पहुंच गई है है तो अब वह उत्तर प्रदेश में राजनीतिक पार्टी भी नहीं रही है पार्टी विद्युत रिप्रेजेंटेटिव वाली स्थिति में पहुंच गई तो यह मामला है कि आप अपने नायक के लिए प्रस्तुत कर रहे हैं या आप अपनी विचारधारा के जो मुद्दे हैं और विचारधारा के चलते सत्तासीन शक्तियों से जो आपकी असहमतियां हैं उनके प्रति पुरस्कार हैं आप जिस एग्रीमेंट के खिलाफ खड़े हैं या आप एक कंटेस्टेंट के साथ में खड़े हैं जिसको कि इलेक्ट्रोलाइट डिस्फंक्शन है अरे आप यह सोचो कि इस देश में यह लोग रहते रहते हैं सेक्युलरिज्म के हम सर्कुलर ताकत हैं यह मैंने एक भी प्रोटेस्ट नहीं देखा सांप्रदायिकता के खिलाफ जो पार्टियां बोलती है कि उसके खिलाफ लड़ रहे हैं कहां लड़ रहे हैं आप वीर वे मैंने देखा ही नहीं इतने मतलब कभी-कभी इससे बहुत होता है मुझे नहीं चाहिए है क्रोध भी होता है कि यार सब आदमी ट्विटर पर ही लड़ोगे वहीं जमीन पर कोई जमीन पर आकर माहौल तो बनाओ यह नहीं चलेगा अगर आपको पसंद नहीं है तो लेकिन ताकि इसमें एक जगह पर सहमति है और वह हो गया है मैंने जो मैंने अपनी जवानी में घ्र घ्र और और विधायकों को मनाने की परंपरा ख़त्म नहीं कर रही है आप समझ रहे हैं अगर कांग्रेस में नेटवर्क है तो आप बोलते हो तो कोशिश करें कि मैं यहां से खिलाफ माहौल बनाने की तरह के सामने रूट पर पहुंचना ऐसे कोई पल्ला झाड़ने का टास्क दिया गया हो एक त ई हैव टो ट्रस्ट कांग्रेस को अगर लगता है कि वाकई हालत खराब हो गई है तो 1 लाख कार्यकर्ताओं को ले करके एक लाइक तो हो गई इस पर फिर इतनी बुरी स्थिति होगी दिल्ली में कार्य करता हूं पुश करवा दीजिए दिल्ली नहीं हुए हैं क्या प्रोटेस्ट जिसमें लाखों लोग पहुंचे हजारों लोग पहुंचे आप क्यों नहीं कर सकते वॉच पर आपको ललकारने के लिए 1991 में एक बड़ी रैली बोर्ड लपेट कर सकते हैं प्रोफेट मोहम्मद के कार्टून के विवाद पर मुसलमानों के लाख से ऊपर की तादाद का प्रोटेस्ट दिल्ली में हुआ था और उस समय हुआ था जब जॉर्ज बुश यहां आने वाले थे और उस समय वर्ड इस कार्टून से हमारा कोई लेना-देना नहीं था जो कि अब मैं आपको बनाना यहां के लोगों ने उसकी कोई हार्ड कॉपी देखी और इंटरनेट व्हाट्सएप तथा नहीं Facebook नहीं था बिना सोशल मीडिया के इतना प्रोटेस्ट हो गया था तो अब क्यों नहीं हो रहा है कांग्रेस अगर वाकई उद्वेलित है अपनी लीडरशिप से लेकर के और देश के तमाम सारे मुद्दों तक पहुंचे यहां पर व्यवसायियों पर यह उसने हो पा रहा है जबकि इस से ज्यादा दुख कुछ नहीं हो सकता है कि लोकतंत्र का जो आइकन है गवर्नेंस का वह भूख नहीं है वह कंस्ट्रेशन नहीं बुलडोजर है आज की तारीख में और लोगों को यह भी चैन नहीं करता है राजनीतिक पार्टियों को ही बाद भी चैन नहीं करती है कि लोकतंत्र में सत्ता और शासन और गवर्नेंस का जो संकेत है वह आपकी होली बुक कांस्टीट्यूशन आफ इंडिया ना रह करके अब यह हो गया है बोलोगे चढ़ा दूंगा का यह निकलोगे इस गिरा दूंगा तो फिर बोलोगे तो फिर अ बहुत उसके बाद अगर बोलते हैं तो गाड़ी पलट जाएगी अरे 75 साल की बुढ़िया लोकतंत्र राहुल गांधी के तुगलक लेन के घर के आगे रोती भी पड़ी मिलेगी ना तो वह ट्वीट कर देंगे कि पहले जाएंगे दिक्कत मैं उसे उदाहरण दे रहा हूं का सभी नेताओं का आजकल भी हो गया कोई स्टडी देखते हैं कि उनका ट्विटर पर इंगेजमेंट मोदी जी से ज्यादा है प्रेसिडेंट इंगेजमेंट तरफ मोदी जी ने खुद बहुत अच्छा तुम्हारा ज्यादा है तो जमीन पर इंगेजमेंट इंगेजमेंट की बहुत जरूरत है कि किस तरह से इस पर डिपेंड करता है कि प्रदर्शनों में जाते हैं वाले कार्यकर्ता उनके दोनों हाथ दोनों श्रेष्ठ होते हैं और पुलिस वालों ने उन्हें पकड़कर और वह तस्वीर होती है और जो कर्मठ कार्यकर्ता है वह तस्वीर खिंचवा घ्र को सब्सक्राइब कि वो लोग बड़े हैरान करते हैं जिनको गिरफ्तारी के बाद बस में बैठा लिया गया फिर जब एक कैमरा बगल से गुजरा तो बस की खिड़की से निकलकर मूर्तियां सिलेक्शन का यह कितना कितना लेस पर है यह मैं और हमारे तो अब जैसे लल्लूभाई हैं यूपी में उनका कमाल है वह सवेरे अरेस्ट थे यह वाले में 59 दिनों सवेर इस अवसर मुख्य सबसे पहले मुझे गिरफ्तार किए थे सिंगल लार्जेस्ट तो तुरंत करता हूं तुमको यह भी सकता है वैसे प्रदेश अध्यक्ष प्रदीप",
  "search_text": "\nTitle: कांग्रेस का ‘Electile Dysfunction’, Protest के अलबेले किरदार और जवानी के झामफाड़ गाने Teen Taal\n\nEpisode ID: s01_e088\n\nContent:\n\nहैं तो यह जिम्मेदारी राज्य सरकारों की है आप सरकार में है इसका यह मतलब नहीं है कि आप जो चाहते हैं वह हो आप सरकार में हैं इसका यह मतलब है कि लोग जो चाहते हैं आप वह करो आपको उसके लिए वहां पर बैठाया है और बताओ कहने कि यह तो बहुत राष्ट्रपति पद जैसी बातें कर रहे हो तुम बाबा लोकतंत्र में प्रोटेस्ट होता है और कॉन्टेक्स्ट आफ प्रोटेस्ट आपको लगता है कि नहीं हो पा रहा हुं करते हैं और फिर से करते हैं ताकि इसमें जो है वह कांटेस्ट की प्रोटेस्ट की नहीं है है तो यह है और जो ताऊ बात कह गया भी बहुत बारिश की प्रोटेस्ट को समझना बहुत जरूरी है कि कौन से पोर्टल ज़मीन है और कौन से दरअसल कांटेस्ट की प्रोटेस्ट जैसे किसान जब न्यूनतम मजदूरी की भूमि अधिग्रहण की बात करने के लिए रोड पर उतरा कि जब आया तो उसकी मंशा यह कांटेस्ट की नहीं है उसको जा करके चुनाव मैदान में वहां पर है कि भई यह करो भैया आपने कभी नहीं लेकिन यह कांटेस्ट कि मेरी फोटो अगर बार इंडिया टुडे और आजतक चैनल पर आती रहेगी जिसमें चार लोग मुझे ना किए हुए हैं तो संभव है कि टिकट मिल जाए एमपी विधायक और राज्य सभा संकट यह है कि यह सारी महत्वाकांक्षाएं उनको रोड पर की तरह शरीर की तरह मृत्यु करा रहे हैं लेकिन इस दौरान जब यह सब कुछ हो रहा है उत्तर प्रदेश की विधानसभा की कांग्रेस विधान परिषद में भी शून्य पर पहुंच गई है है तो अब वह उत्तर प्रदेश में राजनीतिक पार्टी भी नहीं रही है पार्टी विद्युत रिप्रेजेंटेटिव वाली स्थिति में पहुंच गई तो यह मामला है कि आप अपने नायक के लिए प्रस्तुत कर रहे हैं या आप अपनी विचारधारा के जो मुद्दे हैं और विचारधारा के चलते सत्तासीन शक्तियों से जो आपकी असहमतियां हैं उनके प्रति पुरस्कार हैं आप जिस एग्रीमेंट के खिलाफ खड़े हैं या आप एक कंटेस्टेंट के साथ में खड़े हैं जिसको कि इलेक्ट्रोलाइट डिस्फंक्शन है अरे आप यह सोचो कि इस देश में यह लोग रहते रहते हैं सेक्युलरिज्म के हम सर्कुलर ताकत हैं यह मैंने एक भी प्रोटेस्ट नहीं देखा सांप्रदायिकता के खिलाफ जो पार्टियां बोलती है कि उसके खिलाफ लड़ रहे हैं कहां लड़ रहे हैं आप वीर वे मैंने देखा ही नहीं इतने मतलब कभी-कभी इससे बहुत होता है मुझे नहीं चाहिए है क्रोध भी होता है कि यार सब आदमी ट्विटर पर ही लड़ोगे वहीं जमीन पर कोई जमीन पर आकर माहौल तो बनाओ यह नहीं चलेगा अगर आपको पसंद नहीं है तो लेकिन ताकि इसमें एक जगह पर सहमति है और वह हो गया है मैंने जो मैंने अपनी जवानी में घ्र घ्र और और विधायकों को मनाने की परंपरा ख़त्म नहीं कर रही है आप समझ रहे हैं अगर कांग्रेस में नेटवर्क है तो आप बोलते हो तो कोशिश करें कि मैं यहां से खिलाफ माहौल बनाने की तरह के सामने रूट पर पहुंचना ऐसे कोई पल्ला झाड़ने का टास्क दिया गया हो एक त ई हैव टो ट्रस्ट कांग्रेस को अगर लगता है कि वाकई हालत खराब हो गई है तो 1 लाख कार्यकर्ताओं को ले करके एक लाइक तो हो गई इस पर फिर इतनी बुरी स्थिति होगी दिल्ली में कार्य करता हूं पुश करवा दीजिए दिल्ली नहीं हुए हैं क्या प्रोटेस्ट जिसमें लाखों लोग पहुंचे हजारों लोग पहुंचे आप क्यों नहीं कर सकते वॉच पर आपको ललकारने के लिए 1991 में एक बड़ी रैली बोर्ड लपेट कर सकते हैं प्रोफेट मोहम्मद के कार्टून के विवाद पर मुसलमानों के लाख से ऊपर की तादाद का प्रोटेस्ट दिल्ली में हुआ था और उस समय हुआ था जब जॉर्ज बुश यहां आने वाले थे और उस समय वर्ड इस कार्टून से हमारा कोई लेना-देना नहीं था जो कि अब मैं आपको बनाना यहां के लोगों ने उसकी कोई हार्ड कॉपी देखी और इंटरनेट व्हाट्सएप तथा नहीं Facebook नहीं था बिना सोशल मीडिया के इतना प्रोटेस्ट हो गया था तो अब क्यों नहीं हो रहा है कांग्रेस अगर वाकई उद्वेलित है अपनी लीडरशिप से लेकर के और देश के तमाम सारे मुद्दों तक पहुंचे यहां पर व्यवसायियों पर यह उसने हो पा रहा है जबकि इस से ज्यादा दुख कुछ नहीं हो सकता है कि लोकतंत्र का जो आइकन है गवर्नेंस का वह भूख नहीं है वह कंस्ट्रेशन नहीं बुलडोजर है आज की तारीख में और लोगों को यह भी चैन नहीं करता है राजनीतिक पार्टियों को ही बाद भी चैन नहीं करती है कि लोकतंत्र में सत्ता और शासन और गवर्नेंस का जो संकेत है वह आपकी होली बुक कांस्टीट्यूशन आफ इंडिया ना रह करके अब यह हो गया है बोलोगे चढ़ा दूंगा का यह निकलोगे इस गिरा दूंगा तो फिर बोलोगे तो फिर अ बहुत उसके बाद अगर बोलते हैं तो गाड़ी पलट जाएगी अरे 75 साल की बुढ़िया लोकतंत्र राहुल गांधी के तुगलक लेन के घर के आगे रोती भी पड़ी मिलेगी ना तो वह ट्वीट कर देंगे कि पहले जाएंगे दिक्कत मैं उसे उदाहरण दे रहा हूं का सभी नेताओं का आजकल भी हो गया कोई स्टडी देखते हैं कि उनका ट्विटर पर इंगेजमेंट मोदी जी से ज्यादा है प्रेसिडेंट इंगेजमेंट तरफ मोदी जी ने खुद बहुत अच्छा तुम्हारा ज्यादा है तो जमीन पर इंगेजमेंट इंगेजमेंट की बहुत जरूरत है कि किस तरह से इस पर डिपेंड करता है कि प्रदर्शनों में जाते हैं वाले कार्यकर्ता उनके दोनों हाथ दोनों श्रेष्ठ होते हैं और पुलिस वालों ने उन्हें पकड़कर और वह तस्वीर होती है और जो कर्मठ कार्यकर्ता है वह तस्वीर खिंचवा घ्र को सब्सक्राइब कि वो लोग बड़े हैरान करते हैं जिनको गिरफ्तारी के बाद बस में बैठा लिया गया फिर जब एक कैमरा बगल से गुजरा तो बस की खिड़की से निकलकर मूर्तियां सिलेक्शन का यह कितना कितना लेस पर है यह मैं और हमारे तो अब जैसे लल्लूभाई हैं यूपी में उनका कमाल है वह सवेरे अरेस्ट थे यह वाले में 59 दिनों सवेर इस अवसर मुख्य सबसे पहले मुझे गिरफ्तार किए थे सिंगल लार्जेस्ट तो तुरंत करता हूं तुमको यह भी सकता है वैसे प्रदेश अध्यक्ष प्रदीप\n"
}