{
  "chunk_id": "s01_e019_c0008",
  "episode_id": "s01_e019",
  "season": 1,
  "episode": 19,
  "part": null,
  "bonus": false,
  "title": "IPL की अटपटी नीलामी और मारवाड़ियों-गुजरातियों के कारोबारी हुनर की समीक्षा Teen Taal, Ep 19",
  "chunk_index": 8,
  "word_count": 1000,
  "text": "अंग्रेजी को हिंदी में करते हैं उसमें नियुक्त किया है एक बहुत मशहूर था वह बल्ध एक होटल का कि वो मीट मॉल जगह में रखा हुआ था तो आप जैसा होता है उसमें उन्होंने क्विक में मीट बाहर निकालता तो वह मीटर नहीं बोलते तुम हो गया था और कभी नहीं बोलते वह Bigg Boss टिप्सी पाकिस्तान तो बोल भी लिखा हुआ है उसका ऊपर इंग्लिश ट्रांसलेशन अगर आप गूगल ट्रांसलेट तो तो नीचे क्योंकि तो ऐसी यह दूसरी तरफ सब्सक्राइब ऊपर नीचे डिश को सब्सक्राइब करने में मदद करता है हंसी वाला नहीं होता कि को टाइट हो गया है फिर भी एक बार और आज आप लगाकर घुमाएंगे वाला अनुभव करता था तो एक ब्रांड है जूते का उसके जूते लेकर क्या बोला मैं लकड़ भूमि के जूते लेकर आया हूं रुत कि उसी को बोलता था केंद्रीय प्रसंस्करण इकाई के कुछ हिंदी बताएं अगर हिंदी भी समझ नहीं पा रहे हैं पर मैं सोचता था कि कि कुछ लोग बोलते रखेंगे इस तो महसूस तक अगर हिंदी में मेरा नाम है तो तक किसी होना चाहिए कि फिर मैंने इसका प्रयोग किया था वह सीन तो आप लिखते लिखते हैं कि वह अलग चीज पर अपने जो यह जबरदस्ती बचपन में छोटा पूरे पूरा को लेकर पूरे तो मरे और और व्यवस्था तक रेस्ट पूरी स्कूल टिफिन से ऐसा 21 पूरी लिस्ट है और 615 नगरीय से यह जेलों में रहने वाले लोग अमेरिका बनाने वाले लोग सोचते होंगे कि बाइक इन दो बसों के नंबर की बात कर रहा हूं ड्यूटी संगे 615 मदीने 621 को डीलिस्ट पूर्वांचल अंतरराष्ट्रीय 615 हां जो स्थापना की थी और वह है नहीं कि समझी गई जो हमारी तो क्या हुआ कुछ और है या कुछ और है है अरे गूगल पर निर्भरता की वजह से भी अर्थ का अनर्थ हुआ है घ्र मे ट्रांसलेट टू यूज करते हैं इसमें घृतकुमारी की जगह पर रोक कर रहे हैं क्योंकि वहां पर खर्च नहीं करना चाहते हैं क्वालिटी पर इनवेस्ट करना लोगों को लगती है ऐसे समय में जब दुनिया की तमाम कंपनियां कर रही हैं गैस से कई लोगों के बारे में उन्होंने कहा कि अब हम कोरिया में चाहिए तो हो गया लेकिन फिर भी उन्होंने किया और और अच्छे-अच्छे तय कर पाए नमस्कार पाए लेकिन हम पता नहीं क्यों यह सोचते हैं कि अनुवाद अरे खर्च करना या अनुवाद को महत्त्व देना या अनुवाद को एक गंभीर विधायक के रुप में देखना यह कलर है और इसके वैसे जो केवल यह नुकसान नहीं है इसमें से नुकसान यह है कुछ भी पता हुं कि आप यह देखिए कि बांग्ला का मलयालम का तमिल का तेलुगू का नॉर्थ ईस्ट का यहां तक कि बघेली बुंदेली जो अ छत्तीसगढ़ की भाषाएं हैं उन्हें का अंतर कितना सारा रिछपाल जब उनसे उनके लोकगीत भी उन वह लोगों को एक्सपोज़ है ही नहीं हिंदी के लोगों से पहले हम को लगता है उन्होंने रामचरित मानस से पद्मावत अपनी सारी दुनिया खत्म हो जाएगी या चंदरबरदाई के वहां से शुरू होकर के और फिर बस यह और यह अपना हरिओम पवार तक सारी काव्य रचना है दास्तान उनको समझा नहीं आता है कि और कहां पर चाहिए व्यापारी को लोगों ने पहले ही नहीं और लोग सफर करते हैं कि यह भारत हमारा देश है आप गर्व से बने रहना चाहते हैं बेटा भाषाओं भोजन सामग्रियों को घना उनके रहन-सहन खान-पान को अंगीकृत किए बिना आप भारतीय बने रहना चाहते इस देश को अनुवाद जॉब मिल सकता था अनुवाद हमारा एक नेशनल इंटीग्रेशन मिशन होना चाहिए था हमने उसके ऊपर कभी ध्यान नहीं दिया हमने उसको कभी कभी Bigg Boss ने दिया तो यह बहुत आनंद की मनोरंजन की मजे की बात लग सकती है कि अनुवाद में इस तरह की गलतियां हो रही हैं लेकिन अनुवाद दार्शनिक बहुत दर्दनाक कहानी है इस देश में किन चीजों को हमने छोड़ दिया अपने नायकों को अपने श्रेष्ठ लोगों को अपने श्रेष्ठ चिंतन को अपनी श्रेष्ठ रचनाओं को लिस्ट परंपराओं को हमने बताने के हर दरवाजे के मुहाने पर पथ्थर लगती है लोगों को सीमित रखा कि वह अपनी भाषा ही बोली और अपने ही कुनबे के आसपास रहा है और वहीं पर उसी को तक संसार मानते रहे वैंकूवर में रहो हां महक उन्हें अपने कुएं में पैदा हुए थे और गीत गाए जाते थे तो हम अपने प्रदेशों में और अपने-अपने देशों में उलझ कर रह गए पटेल जयेश पटेल साथ शेयर कर सकते हैं लेकिन इसके ऊपर चाहिए कि मुझे देखना है और अब और उसमें कितना सच कितना होता है स्थिति देखिए कि अंग्रेजी में अगर किसी ने किसी को गाली दी किसी भी तरह की काली अउ सकते हिंदी में अनुवाद किया उसने मुझे सड़ा हुआ तरबूज कहा कि फिल्म का अनुवाद हो रहा है वह बहुत ही अर्घ्य खराब अनुवाद की समस्या को एक बार बसपा सांसद धनंजय सिंह यादव ने राज्यसभा में उठाया और उन्होंने जिक्र किया था अंग्रेजी में लिखे सब्सक्राइब जो है वह यह सब्सक्राइब करें और अगर आपने सब्सक्राइब नहीं दूसरे को जाएंगे दूर चली जाऊंगी सीरियल ले जाएंगे इससे पहले विचारोत्तेजक खबर है और खबर कहां से इस बारे में मालूम नहीं कि मतलब बच्चों के नाम रखने को लेकर के पूरी दुनिया में लिखित करार है कि बच्चों के नाम सोचते हैं अपने घर परिवार तो यह हमारे आस-पास में रिश्तेदार में बुआ जी के यहां के बच्चे का नाम की एक महिला ने अपने बच्चे का नाम रखे हैं उनकी कॉपी कर लेती है इसको पोर्टल पर इसलिए नहीं बता सकते कि किस जगह की घटना में हैं और उनका कहना है कि उनकी बहन को पहली लड़की हुई बेटी हुई तो उन्होंने तो लगा कि कोई उस कि कम से कम लिंग का तो डिफरेंस है वह लड़की है मेरा बेटा है स्टेज चलने मगर हद तो तब हो गई जब यह पता चला कि उनकी बहन दोबारा प्रेग्नेंट हुई है और 3 महीने में बच्चे की डिलीवरी से पहले बहन कर दिया कि उसका नाम डू यू थिंक इट इज एक्टिव वो अपने सब्सक्राइब तो एक उनके यहां पर",
  "search_text": "\nTitle: IPL की अटपटी नीलामी और मारवाड़ियों-गुजरातियों के कारोबारी हुनर की समीक्षा Teen Taal, Ep 19\n\nEpisode ID: s01_e019\n\nContent:\n\nअंग्रेजी को हिंदी में करते हैं उसमें नियुक्त किया है एक बहुत मशहूर था वह बल्ध एक होटल का कि वो मीट मॉल जगह में रखा हुआ था तो आप जैसा होता है उसमें उन्होंने क्विक में मीट बाहर निकालता तो वह मीटर नहीं बोलते तुम हो गया था और कभी नहीं बोलते वह Bigg Boss टिप्सी पाकिस्तान तो बोल भी लिखा हुआ है उसका ऊपर इंग्लिश ट्रांसलेशन अगर आप गूगल ट्रांसलेट तो तो नीचे क्योंकि तो ऐसी यह दूसरी तरफ सब्सक्राइब ऊपर नीचे डिश को सब्सक्राइब करने में मदद करता है हंसी वाला नहीं होता कि को टाइट हो गया है फिर भी एक बार और आज आप लगाकर घुमाएंगे वाला अनुभव करता था तो एक ब्रांड है जूते का उसके जूते लेकर क्या बोला मैं लकड़ भूमि के जूते लेकर आया हूं रुत कि उसी को बोलता था केंद्रीय प्रसंस्करण इकाई के कुछ हिंदी बताएं अगर हिंदी भी समझ नहीं पा रहे हैं पर मैं सोचता था कि कि कुछ लोग बोलते रखेंगे इस तो महसूस तक अगर हिंदी में मेरा नाम है तो तक किसी होना चाहिए कि फिर मैंने इसका प्रयोग किया था वह सीन तो आप लिखते लिखते हैं कि वह अलग चीज पर अपने जो यह जबरदस्ती बचपन में छोटा पूरे पूरा को लेकर पूरे तो मरे और और व्यवस्था तक रेस्ट पूरी स्कूल टिफिन से ऐसा 21 पूरी लिस्ट है और 615 नगरीय से यह जेलों में रहने वाले लोग अमेरिका बनाने वाले लोग सोचते होंगे कि बाइक इन दो बसों के नंबर की बात कर रहा हूं ड्यूटी संगे 615 मदीने 621 को डीलिस्ट पूर्वांचल अंतरराष्ट्रीय 615 हां जो स्थापना की थी और वह है नहीं कि समझी गई जो हमारी तो क्या हुआ कुछ और है या कुछ और है है अरे गूगल पर निर्भरता की वजह से भी अर्थ का अनर्थ हुआ है घ्र मे ट्रांसलेट टू यूज करते हैं इसमें घृतकुमारी की जगह पर रोक कर रहे हैं क्योंकि वहां पर खर्च नहीं करना चाहते हैं क्वालिटी पर इनवेस्ट करना लोगों को लगती है ऐसे समय में जब दुनिया की तमाम कंपनियां कर रही हैं गैस से कई लोगों के बारे में उन्होंने कहा कि अब हम कोरिया में चाहिए तो हो गया लेकिन फिर भी उन्होंने किया और और अच्छे-अच्छे तय कर पाए नमस्कार पाए लेकिन हम पता नहीं क्यों यह सोचते हैं कि अनुवाद अरे खर्च करना या अनुवाद को महत्त्व देना या अनुवाद को एक गंभीर विधायक के रुप में देखना यह कलर है और इसके वैसे जो केवल यह नुकसान नहीं है इसमें से नुकसान यह है कुछ भी पता हुं कि आप यह देखिए कि बांग्ला का मलयालम का तमिल का तेलुगू का नॉर्थ ईस्ट का यहां तक कि बघेली बुंदेली जो अ छत्तीसगढ़ की भाषाएं हैं उन्हें का अंतर कितना सारा रिछपाल जब उनसे उनके लोकगीत भी उन वह लोगों को एक्सपोज़ है ही नहीं हिंदी के लोगों से पहले हम को लगता है उन्होंने रामचरित मानस से पद्मावत अपनी सारी दुनिया खत्म हो जाएगी या चंदरबरदाई के वहां से शुरू होकर के और फिर बस यह और यह अपना हरिओम पवार तक सारी काव्य रचना है दास्तान उनको समझा नहीं आता है कि और कहां पर चाहिए व्यापारी को लोगों ने पहले ही नहीं और लोग सफर करते हैं कि यह भारत हमारा देश है आप गर्व से बने रहना चाहते हैं बेटा भाषाओं भोजन सामग्रियों को घना उनके रहन-सहन खान-पान को अंगीकृत किए बिना आप भारतीय बने रहना चाहते इस देश को अनुवाद जॉब मिल सकता था अनुवाद हमारा एक नेशनल इंटीग्रेशन मिशन होना चाहिए था हमने उसके ऊपर कभी ध्यान नहीं दिया हमने उसको कभी कभी Bigg Boss ने दिया तो यह बहुत आनंद की मनोरंजन की मजे की बात लग सकती है कि अनुवाद में इस तरह की गलतियां हो रही हैं लेकिन अनुवाद दार्शनिक बहुत दर्दनाक कहानी है इस देश में किन चीजों को हमने छोड़ दिया अपने नायकों को अपने श्रेष्ठ लोगों को अपने श्रेष्ठ चिंतन को अपनी श्रेष्ठ रचनाओं को लिस्ट परंपराओं को हमने बताने के हर दरवाजे के मुहाने पर पथ्थर लगती है लोगों को सीमित रखा कि वह अपनी भाषा ही बोली और अपने ही कुनबे के आसपास रहा है और वहीं पर उसी को तक संसार मानते रहे वैंकूवर में रहो हां महक उन्हें अपने कुएं में पैदा हुए थे और गीत गाए जाते थे तो हम अपने प्रदेशों में और अपने-अपने देशों में उलझ कर रह गए पटेल जयेश पटेल साथ शेयर कर सकते हैं लेकिन इसके ऊपर चाहिए कि मुझे देखना है और अब और उसमें कितना सच कितना होता है स्थिति देखिए कि अंग्रेजी में अगर किसी ने किसी को गाली दी किसी भी तरह की काली अउ सकते हिंदी में अनुवाद किया उसने मुझे सड़ा हुआ तरबूज कहा कि फिल्म का अनुवाद हो रहा है वह बहुत ही अर्घ्य खराब अनुवाद की समस्या को एक बार बसपा सांसद धनंजय सिंह यादव ने राज्यसभा में उठाया और उन्होंने जिक्र किया था अंग्रेजी में लिखे सब्सक्राइब जो है वह यह सब्सक्राइब करें और अगर आपने सब्सक्राइब नहीं दूसरे को जाएंगे दूर चली जाऊंगी सीरियल ले जाएंगे इससे पहले विचारोत्तेजक खबर है और खबर कहां से इस बारे में मालूम नहीं कि मतलब बच्चों के नाम रखने को लेकर के पूरी दुनिया में लिखित करार है कि बच्चों के नाम सोचते हैं अपने घर परिवार तो यह हमारे आस-पास में रिश्तेदार में बुआ जी के यहां के बच्चे का नाम की एक महिला ने अपने बच्चे का नाम रखे हैं उनकी कॉपी कर लेती है इसको पोर्टल पर इसलिए नहीं बता सकते कि किस जगह की घटना में हैं और उनका कहना है कि उनकी बहन को पहली लड़की हुई बेटी हुई तो उन्होंने तो लगा कि कोई उस कि कम से कम लिंग का तो डिफरेंस है वह लड़की है मेरा बेटा है स्टेज चलने मगर हद तो तब हो गई जब यह पता चला कि उनकी बहन दोबारा प्रेग्नेंट हुई है और 3 महीने में बच्चे की डिलीवरी से पहले बहन कर दिया कि उसका नाम डू यू थिंक इट इज एक्टिव वो अपने सब्सक्राइब तो एक उनके यहां पर\n"
}