{
  "chunk_id": "s02_e045_c0020",
  "episode_id": "s02_e045",
  "season": 2,
  "episode": 45,
  "part": null,
  "bonus": false,
  "title": "VIP की हिरासत, ED का Full Form और Driverless car Teen Taal S2 E45 Shams Tahir Khan",
  "chunk_index": 20,
  "word_count": 1000,
  "text": "कुछ सोच के रुक गया था उसी को वापस भेजते भी वहां तो काट दे आप गाड़ी लेकर गए गाड़ी पार कर दी उसके बाद थोड़ी देर के बाद आप आए आपने देखा कि हां खाना वाना करीम खा करर आ गया एक पहिया गायब ठीक है अब आप क्या करेंगे उस आलम में तो अचानक दो तीन लड़के आ क्या हुआ साहब यार ये पैया किसी ने चला अरे ये आप यहां क्यों गाड़ी रहे ऐसी लोग हैं ये वो तोलता है कि कैसे जाऊंगा तो बोला है एक दो दुकान मैं ढूंढता हूं उसके बाद वो जाएगा वो आएगा एक फिर गाड़ी देखेगा पैया देखेगा बोला ठीक है इतने पैसे वो मरता क्या करता लगा दो अब आया उस उसी का पया उसी बंदे को पता भी है बोल भी देता है य तो मेरा पया लग रहा है कता है तो फिर आई डट नो क्या कर सकते पैसे तो देने पड़ेंगे चार नहीं करते जामा मस्जिद में ये बात है कभी कभी चार भी किया उन्होंने ये सब कुछ वही प होता है जहां प सबसे ज्यादा जो चीज होती है ना 50 मीटर की दूरी जमा मस्जिद पुलिस स्टेशन है अच्छा और वो बाय द वे चढ़ाते भी है इंतजार करते उसके आने का करीम से पूरा खाके निहारी वारी निकलेगा एकदम आते ओ तेरी की ये क्या हुआ ऐसे की उसको पता नहीं चलेगा बहुत मजे लेते ये जो चोर बाजार का कांसेप्ट है मतलब सब जगह हम सुनते हैं वहां पर एक चोर बाजार है कते लाल किल्ले के सामने चोर बाजार लगता है म ये तो तरह से चोरी का सामान बिक रहा है तो तो इलीगल है जब लोगों को पता है पुलिस वालों को नहीं पता होता क्या उस कुछ अब तो लाल किले के पीछे वाला बंद हो गया बंद हो गया बट लगा बचपन में मैंने बहुत सामान खरीदा वहां से मैंने कैम वो कैसे चल पा मैंने भी इलेक्ट्रॉनिक्स वहां से खरीदे इलेक्स खरीदा सस्ता स्टीरियो स्टीरियो खरीदा है वहां से एक्चुअली उसको चोर मार्केट तो हम लोग उस नाम से जानते हैं ना का हा वो पुराने भी होते थे जैसे एक होता है ना कि किसी बहुत सारे आप जींस जैकेट शूज ये भी सब मिलता था तो यह भी होता था कि यार कुछ एंबेसी के पुराने जो शिफ्ट हो रहे हैं तो उनका सामान नीलाम हो गया यहां बिक रहा है उसी में चोरी का भी चला जाता था लेकिन उस चोर मार्केट से बहुत लोगों का भला हुआ मतलब जो चीजें अच्छे-अच्छे ब्रांड की इतनी सस्ती और कहीं नहीं मिल सकती थी स और खास तौर पर उसका अट्रैक्शन था तब मैं दिल्ली यूनिवर्सिटी में था मुझे मालूम है सारे डीयू के लड़के संडे वहीं पहुंचते थे 12:30 वाला पास तो था ही डीटीसी का रेस्टोरेंट पास फर्स्ट कम फर्स्ट सर्व होता है वो तो जितना जल्दी पहुंचेंगे माल उतना एक बात देखो क्या होता है सर मैं आपको बेचू रोलेक्स 000 में तो आप कहोगे नकली है मैं कहूंगा चोरी का है हम तो ले खरीद लो क्यों आपको यकीन हो जाएगा कि आप ये अभी भी आनंद विहार या आईएसबीटी अड्डे पे आप जाएंगे तो आपके बगल में वो आएगा ऐसे चुप थोड़ा छुपा के दिखाया सर रेबन रेबन है सर अभी ये फैक्ट्री आउटलेट्स है कर लो बहुत धीमे से आपसे फुसफुसाना हो स आपके कुछ ऐसे तो सैलरी मिलती है एक था एक डबल मर्डर हो गया साउथ दिल्ली में तो एक घर में दो लाश पड़ी हुई है बीट अफसर सबसे पहले पहुंचा उसने दोनों लाश देखी वकी टॉकी उठाया और अपने साहब को मैसेज दे रहा है कि साहब जी ये जी के 147 पहली मंजिल पर जी दो मरी हुई डेड बॉडी पड़ी हुई है बस इतना ही था एक अभी था ग्रुप में एक बड़ी अच्छी कहानी रियल स्टोरी थी ये बिना नाम ले एक यूपी पुलिस में इंस्पेक्टर साहब जवाइन हुए और यह हुआ कि उन्होंने देखा कि यार बहुत एनकाउंटर चल रहा है मुझे भी एनकाउंटर करूंगा तो आउट ऑफ प्रमोशन भी होगा थोड़ा नाम भी होगा लगेगा दब्बू अब्बू होनी फिर उन्होंने तय किया कि एनकाउंटर करना है तब सारे दो चार अपने तैयार किया भाई करना है तो फ किसको करें तो पता चला कि एक यहां का घोषित अपराधी था वह जेल में था अभी बेल पे बाहर आया हुआ है तो इसी को ठोक देते हैं तो क हां उसके क्रिमिनल रिकॉर्ड अच्छे खासे हैं शक भी नहीं होगा वाई भी होगी तो उन्होने कहा ठीक है अब कैसे करना है तो यह हुआ कि उसको बुलाते हैं पूछताछ करते हैं उसके बाद उसको ठोक देंगे लेकिन कैसे अभी तो बेल प है तो कुछ क्राइम तो किया नहीं है तो मोटरसाइकिल लटवा हैं पहले अब हुआ कि मोटरसाइकिल लूटो तो पुलिस वाला ही शाम के टाइम में अंधेरा हो रहा है शादी वर्दी में सड़क के किनारे पहुंचा और एक आदमी जा रहा था मोटरसाइकिल पर उसने उसकी मोटरसाइकिल गन पॉइंट में लूटा और उसको भगाया लेके मोटरसाइकिल चला गया और अब आ गया थाने अब बैठे ऐसा कि मोटरसाइकिल आ गई इन्होने छुपा दिया मोटरसाइकिल कि अब वो आएगा रिपोर्ट खाएगा और उसके बाद सीधे उसको उठाएंगे और उसको उठाकर ठोक देंगे अभी थाने में बैठे रिपोर्ट लिखाने नहीं आ रहा है पूरी रात बीत गई नहीं आया अगले दिन आ गया अब इंस्पेक्टर साहब को सरा एनकाउंटर करना है इतना लेट क्यों कर रहा है क्योंकि एफआईआर तो कोई लिखे ना कि मोटरसाइकिल चोरी हुई है तो दूसरा दिन में निकल गया वो रिपोर्ट लिखाने नहीं आया तो इंस्पेक्टर को आ गया गुस्सा उसने कहा या वो कैसा पागल आदमी है उसने कहा जाके पता करो कहां रहता है वो गांव था छोटा सा वो गए भाई कौन है ये तोव मिला बोला तुम्हारी मोटरसाइकिल वा किसी ने छीन ली बोला हां साहब लूट लिया उसने तो तुम रिपोर्ट लिखाने नहीं आया बोला अरे मैं तो वैसे ही उससे पीछा छुड़ाना चाह रहा था मैं तो बेचने के चक्कर में था पैसा ही नहीं दे",
  "search_text": "\nTitle: VIP की हिरासत, ED का Full Form और Driverless car Teen Taal S2 E45 Shams Tahir Khan\n\nEpisode ID: s02_e045\n\nContent:\n\nकुछ सोच के रुक गया था उसी को वापस भेजते भी वहां तो काट दे आप गाड़ी लेकर गए गाड़ी पार कर दी उसके बाद थोड़ी देर के बाद आप आए आपने देखा कि हां खाना वाना करीम खा करर आ गया एक पहिया गायब ठीक है अब आप क्या करेंगे उस आलम में तो अचानक दो तीन लड़के आ क्या हुआ साहब यार ये पैया किसी ने चला अरे ये आप यहां क्यों गाड़ी रहे ऐसी लोग हैं ये वो तोलता है कि कैसे जाऊंगा तो बोला है एक दो दुकान मैं ढूंढता हूं उसके बाद वो जाएगा वो आएगा एक फिर गाड़ी देखेगा पैया देखेगा बोला ठीक है इतने पैसे वो मरता क्या करता लगा दो अब आया उस उसी का पया उसी बंदे को पता भी है बोल भी देता है य तो मेरा पया लग रहा है कता है तो फिर आई डट नो क्या कर सकते पैसे तो देने पड़ेंगे चार नहीं करते जामा मस्जिद में ये बात है कभी कभी चार भी किया उन्होंने ये सब कुछ वही प होता है जहां प सबसे ज्यादा जो चीज होती है ना 50 मीटर की दूरी जमा मस्जिद पुलिस स्टेशन है अच्छा और वो बाय द वे चढ़ाते भी है इंतजार करते उसके आने का करीम से पूरा खाके निहारी वारी निकलेगा एकदम आते ओ तेरी की ये क्या हुआ ऐसे की उसको पता नहीं चलेगा बहुत मजे लेते ये जो चोर बाजार का कांसेप्ट है मतलब सब जगह हम सुनते हैं वहां पर एक चोर बाजार है कते लाल किल्ले के सामने चोर बाजार लगता है म ये तो तरह से चोरी का सामान बिक रहा है तो तो इलीगल है जब लोगों को पता है पुलिस वालों को नहीं पता होता क्या उस कुछ अब तो लाल किले के पीछे वाला बंद हो गया बंद हो गया बट लगा बचपन में मैंने बहुत सामान खरीदा वहां से मैंने कैम वो कैसे चल पा मैंने भी इलेक्ट्रॉनिक्स वहां से खरीदे इलेक्स खरीदा सस्ता स्टीरियो स्टीरियो खरीदा है वहां से एक्चुअली उसको चोर मार्केट तो हम लोग उस नाम से जानते हैं ना का हा वो पुराने भी होते थे जैसे एक होता है ना कि किसी बहुत सारे आप जींस जैकेट शूज ये भी सब मिलता था तो यह भी होता था कि यार कुछ एंबेसी के पुराने जो शिफ्ट हो रहे हैं तो उनका सामान नीलाम हो गया यहां बिक रहा है उसी में चोरी का भी चला जाता था लेकिन उस चोर मार्केट से बहुत लोगों का भला हुआ मतलब जो चीजें अच्छे-अच्छे ब्रांड की इतनी सस्ती और कहीं नहीं मिल सकती थी स और खास तौर पर उसका अट्रैक्शन था तब मैं दिल्ली यूनिवर्सिटी में था मुझे मालूम है सारे डीयू के लड़के संडे वहीं पहुंचते थे 12:30 वाला पास तो था ही डीटीसी का रेस्टोरेंट पास फर्स्ट कम फर्स्ट सर्व होता है वो तो जितना जल्दी पहुंचेंगे माल उतना एक बात देखो क्या होता है सर मैं आपको बेचू रोलेक्स 000 में तो आप कहोगे नकली है मैं कहूंगा चोरी का है हम तो ले खरीद लो क्यों आपको यकीन हो जाएगा कि आप ये अभी भी आनंद विहार या आईएसबीटी अड्डे पे आप जाएंगे तो आपके बगल में वो आएगा ऐसे चुप थोड़ा छुपा के दिखाया सर रेबन रेबन है सर अभी ये फैक्ट्री आउटलेट्स है कर लो बहुत धीमे से आपसे फुसफुसाना हो स आपके कुछ ऐसे तो सैलरी मिलती है एक था एक डबल मर्डर हो गया साउथ दिल्ली में तो एक घर में दो लाश पड़ी हुई है बीट अफसर सबसे पहले पहुंचा उसने दोनों लाश देखी वकी टॉकी उठाया और अपने साहब को मैसेज दे रहा है कि साहब जी ये जी के 147 पहली मंजिल पर जी दो मरी हुई डेड बॉडी पड़ी हुई है बस इतना ही था एक अभी था ग्रुप में एक बड़ी अच्छी कहानी रियल स्टोरी थी ये बिना नाम ले एक यूपी पुलिस में इंस्पेक्टर साहब जवाइन हुए और यह हुआ कि उन्होंने देखा कि यार बहुत एनकाउंटर चल रहा है मुझे भी एनकाउंटर करूंगा तो आउट ऑफ प्रमोशन भी होगा थोड़ा नाम भी होगा लगेगा दब्बू अब्बू होनी फिर उन्होंने तय किया कि एनकाउंटर करना है तब सारे दो चार अपने तैयार किया भाई करना है तो फ किसको करें तो पता चला कि एक यहां का घोषित अपराधी था वह जेल में था अभी बेल पे बाहर आया हुआ है तो इसी को ठोक देते हैं तो क हां उसके क्रिमिनल रिकॉर्ड अच्छे खासे हैं शक भी नहीं होगा वाई भी होगी तो उन्होने कहा ठीक है अब कैसे करना है तो यह हुआ कि उसको बुलाते हैं पूछताछ करते हैं उसके बाद उसको ठोक देंगे लेकिन कैसे अभी तो बेल प है तो कुछ क्राइम तो किया नहीं है तो मोटरसाइकिल लटवा हैं पहले अब हुआ कि मोटरसाइकिल लूटो तो पुलिस वाला ही शाम के टाइम में अंधेरा हो रहा है शादी वर्दी में सड़क के किनारे पहुंचा और एक आदमी जा रहा था मोटरसाइकिल पर उसने उसकी मोटरसाइकिल गन पॉइंट में लूटा और उसको भगाया लेके मोटरसाइकिल चला गया और अब आ गया थाने अब बैठे ऐसा कि मोटरसाइकिल आ गई इन्होने छुपा दिया मोटरसाइकिल कि अब वो आएगा रिपोर्ट खाएगा और उसके बाद सीधे उसको उठाएंगे और उसको उठाकर ठोक देंगे अभी थाने में बैठे रिपोर्ट लिखाने नहीं आ रहा है पूरी रात बीत गई नहीं आया अगले दिन आ गया अब इंस्पेक्टर साहब को सरा एनकाउंटर करना है इतना लेट क्यों कर रहा है क्योंकि एफआईआर तो कोई लिखे ना कि मोटरसाइकिल चोरी हुई है तो दूसरा दिन में निकल गया वो रिपोर्ट लिखाने नहीं आया तो इंस्पेक्टर को आ गया गुस्सा उसने कहा या वो कैसा पागल आदमी है उसने कहा जाके पता करो कहां रहता है वो गांव था छोटा सा वो गए भाई कौन है ये तोव मिला बोला तुम्हारी मोटरसाइकिल वा किसी ने छीन ली बोला हां साहब लूट लिया उसने तो तुम रिपोर्ट लिखाने नहीं आया बोला अरे मैं तो वैसे ही उससे पीछा छुड़ाना चाह रहा था मैं तो बेचने के चक्कर में था पैसा ही नहीं दे\n"
}