{
  "chunk_id": "s02_e030_c0016",
  "episode_id": "s02_e030",
  "season": 2,
  "episode": 30,
  "part": null,
  "bonus": false,
  "title": "Shaitan का वज़न, नाक की खुदाई और तूफ़ानी Auto driver Teen Taal, S2 E30 Comedy Podcast",
  "chunk_index": 16,
  "word_count": 1000,
  "text": "देखना है क्या होता है मतलब पोस्टमार्टम होते हुए देखना था मुझे वो भी मैंने देखा एक जरा सा फैट नहीं होता उनमें दिल का साफ था दिल का साफ था कोई चर्बी नाम की चीज नहीं थी उसम सिर्फ मसल्स लेपट में भी होता है मसल्स उनके फैट होता ही नहीं उ खाने में तेल का उपयोग सीधा र चबाते हैं वो कड़क कड़क कड़क कड़क एक बात है आपने जो बोला ना कि टाइगर देखोगे तो सब कुछ भूल जाओगे ये टाइगर थ की बात तो नहीं कर र कुछ याद ही नहीं र कारण होता है कि आदमी जाता ही देखने के लिए जब आप वैष्णो देवी जाते हो ना इतना किलोमीटर चढ़ के याद रहता देखते ही सब कुछ भूल जाते हो सलीम चिश्ती की दरगाह पर आप जब सूरत से बस पकड़ के आते हो और जैसे ही अंदर जाते हो तो आपके आंख से आंसू निकलने लगते हैं तकलीफ से कित वो तिलिस्म जो सोच के आए थे कि साहब आप देखने आए थे आपको लगता है साक्षात सलीम चिश्ती आपको आशीर्वाद दे रहे हैं इस पर पूरा 6 साल का बेटा होगा ऐसा करके होता है जब आप बोलबम जाते हो ना जब तक वीडियो देखते हो तब तक आपको लगता कैसी नंगई कर रहे हैं लोग देखो श्रद्धा भक्ति होती है ये क्या है इसे नारेबाजी डांस ये सब जब आप जाते हो तो वही करने लगते हो भोले की फौज करेगी मौत आपने जिंदगी में पंजाबी नहीं बोली है हम लेकिन वैष्णो देवी जाते हो तो जय माता दी हम जय माता की नहीं होती है हां सब बोलने लगते हैं ठीक है और जब जहां डीजे पे बोलता है ना कि इस देश का बच्चा बच्चा तो आपका सब सेकुलरिज्म लेे में चला जाता है क्यों क्योंकि आप फिर इसको मास उसको मोबाइल वलगस भी बोलते हैं हम एक दिमाग पे असर होता है जब आदमी कहीं जाकर टाइगर देखने ही गया है और टाइगर देख जाता है तो उस समय लगता है कि दुनिया की सबसे खूबसूरत चीज है हम ताजमहल मैंने पहली बार देखा तो मेरी आंखें फट गई क्या बनाया ब चक्का रह गया मैं क्या बनाया है और मेरे साथ एक मेरा दोस्त था वो कनाडा में रहता है अभी उसने पहले देखा हुआ था उसने ग पर भी ऐसा ही दिखता है सच है सच तो यही है लेकिन आखों से एक्सपीरियंस करना वो तो जब आप किसी चीज को देखने जाते हो एक्सपीरियंस करते हैं तो आपको बहुत वाव लगता है बोल ज लिखाने वाला बहुत दिनों के बाद एक बार जैसे गुजरात लाइन सिर्फ गुजरात में ही है हालाकि कोर्ट ने भी बोला था कि इसे और स्टेट में भेजा जाए राजस्थान कुछ वन उनके लिएट सही है अब हुआ यह है कि वहां प इतने ज्यादा लाइन बढ़ गए हैं उस पूरे जंगल की कैपेसिटी 500 से 550 लायंस हो सकते हैं गिर में गिर में वहां पर 800 से ज्यादा है तो गांव में चल रहे हैं गांव में लोग मुर्गिया मानवान के व कुत्ता बना दिया उनको अच्छा वो भी वहां पे एक तरीके से कैप्ट हो गए क्या गुजरात में रहते हैं ना तो उनको थोड़ा सा वेरियन टाइप का नेचर हो गया झगड़ा वग वो ऐसा नहीं है इनफैक्ट आप गीर में दो बार गया तीसरी बार मैं नहीं गया मतलब अब लायन हो नजरों से गिर गया नजरों से गिर गया गीर तो लायंस बैठे हैं जिप नहीं आ रही आ डंड से हट हट हट हट गाड़ी जाने दो मजा ही नहीं आ रहा सबसे ज्यादा लिपट जो आप कह रहे हैं गुलदार वो गीर में है अच्छा अच्छी बात यह है कि अगर गिर में 300 लेपर्ड की कैपेसिटी 300 लेपर्ड है तो वहां के जो जू है गुजरात में वहां 800 से ज्यादा लेपर्ड सिर्फ उसमें जू में भरे पड़े हुए हैं जिनको उठा उठा के मैटर हो ग बढ़ गए बाहर आ गए डाल रहे हैं अरे उनको जंगल में रिलीज करो यार या दूसरे स् तो लायन अपनी ड्यूटी नहीं कर रहा तो लेपर्ड ही करेगा ना लायन भी मारना आदमी को कौन डराए यार जंगल में घूम रहा है मैं देखता हूं छड़ी लेके घूम रहा है बंदा लायन आए हट हट वहां पे एक ट्राइब है मालधारी जो गाय गर गाय का दूध वगैरह काम करते हैं दूध और दही वगैरह का तो उनके गायों को या मवेशियों को जब वो गाय भैस जो भी होती है जब लाइन मार देते हैं तो वो उसको बाकी जगह प जहर डाल देते हैं उस शिकार पे ताकि दोबारा खाए तोल करने आए तो मर जाए ये कॉर्बेट में और बागड़ में बहुत होता है लेकिन वहां ऐसा नहीं होता वह कहते हैं कि भगवान जंगल में हम रहते हैं और जंगल के भगवान लाय और उन्होंने ये करके प्रसाद अपना लिया है तो उसे माफ कर देते हैं उसमें तो खर वैसे गवर्नमेंट कंपनसेशन भी देती कशन देती है बट कितना देती तुम्हें भी पता और हमें भी पता है इजन कर गुजरात के गुजराती लायंस थोड़ी थोड़ी गुजराती बोलने लगे हैं एनिमेशन बड़ा अच्छा बनेगा जयराज भाई जय श्री कृष्णा कृ लाइन मतलब और लाइन में उतना चाम नहीं है या वो गंदे से दिखते हैं टाइगर रॉयल है अच्छा यह सारा कैट फैमिली पेड़ पर चढ़ जाता है क्या सारा लाइन भी चढ़ जाता है ला मतलब अगर फस जाओ तो लाइन टाइगर ने किल किया था और टाइगर क्या होता मस्त में रहता उस तो राजा है खाना ना खाने के बाद सोने में दूर चला गया अच्छा सफाई पसंद ये बहुत होते हैं किल करके मार के छोड़ देगा य नहीं हबक के खाने लगे पहले दिन रेस्ट करे क् इतनी एनर्जी गई है फिर उसका पेट फाड़ के माल मलीदा सब बाहर निकाल करके और उसको मिट्टी से ढकता है ऐसा भी नहीं कि छोड़ देगा और किल को पकड़ के दूर ले आएगा ढकने की वजह ये होती है कि दुर्गंध या सुगंध तो नहीं कहेंगे दुर्गंध से और जानवर अट्रैक्ट ना हो कर के",
  "search_text": "\nTitle: Shaitan का वज़न, नाक की खुदाई और तूफ़ानी Auto driver Teen Taal, S2 E30 Comedy Podcast\n\nEpisode ID: s02_e030\n\nContent:\n\nदेखना है क्या होता है मतलब पोस्टमार्टम होते हुए देखना था मुझे वो भी मैंने देखा एक जरा सा फैट नहीं होता उनमें दिल का साफ था दिल का साफ था कोई चर्बी नाम की चीज नहीं थी उसम सिर्फ मसल्स लेपट में भी होता है मसल्स उनके फैट होता ही नहीं उ खाने में तेल का उपयोग सीधा र चबाते हैं वो कड़क कड़क कड़क कड़क एक बात है आपने जो बोला ना कि टाइगर देखोगे तो सब कुछ भूल जाओगे ये टाइगर थ की बात तो नहीं कर र कुछ याद ही नहीं र कारण होता है कि आदमी जाता ही देखने के लिए जब आप वैष्णो देवी जाते हो ना इतना किलोमीटर चढ़ के याद रहता देखते ही सब कुछ भूल जाते हो सलीम चिश्ती की दरगाह पर आप जब सूरत से बस पकड़ के आते हो और जैसे ही अंदर जाते हो तो आपके आंख से आंसू निकलने लगते हैं तकलीफ से कित वो तिलिस्म जो सोच के आए थे कि साहब आप देखने आए थे आपको लगता है साक्षात सलीम चिश्ती आपको आशीर्वाद दे रहे हैं इस पर पूरा 6 साल का बेटा होगा ऐसा करके होता है जब आप बोलबम जाते हो ना जब तक वीडियो देखते हो तब तक आपको लगता कैसी नंगई कर रहे हैं लोग देखो श्रद्धा भक्ति होती है ये क्या है इसे नारेबाजी डांस ये सब जब आप जाते हो तो वही करने लगते हो भोले की फौज करेगी मौत आपने जिंदगी में पंजाबी नहीं बोली है हम लेकिन वैष्णो देवी जाते हो तो जय माता दी हम जय माता की नहीं होती है हां सब बोलने लगते हैं ठीक है और जब जहां डीजे पे बोलता है ना कि इस देश का बच्चा बच्चा तो आपका सब सेकुलरिज्म लेे में चला जाता है क्यों क्योंकि आप फिर इसको मास उसको मोबाइल वलगस भी बोलते हैं हम एक दिमाग पे असर होता है जब आदमी कहीं जाकर टाइगर देखने ही गया है और टाइगर देख जाता है तो उस समय लगता है कि दुनिया की सबसे खूबसूरत चीज है हम ताजमहल मैंने पहली बार देखा तो मेरी आंखें फट गई क्या बनाया ब चक्का रह गया मैं क्या बनाया है और मेरे साथ एक मेरा दोस्त था वो कनाडा में रहता है अभी उसने पहले देखा हुआ था उसने ग पर भी ऐसा ही दिखता है सच है सच तो यही है लेकिन आखों से एक्सपीरियंस करना वो तो जब आप किसी चीज को देखने जाते हो एक्सपीरियंस करते हैं तो आपको बहुत वाव लगता है बोल ज लिखाने वाला बहुत दिनों के बाद एक बार जैसे गुजरात लाइन सिर्फ गुजरात में ही है हालाकि कोर्ट ने भी बोला था कि इसे और स्टेट में भेजा जाए राजस्थान कुछ वन उनके लिएट सही है अब हुआ यह है कि वहां प इतने ज्यादा लाइन बढ़ गए हैं उस पूरे जंगल की कैपेसिटी 500 से 550 लायंस हो सकते हैं गिर में गिर में वहां पर 800 से ज्यादा है तो गांव में चल रहे हैं गांव में लोग मुर्गिया मानवान के व कुत्ता बना दिया उनको अच्छा वो भी वहां पे एक तरीके से कैप्ट हो गए क्या गुजरात में रहते हैं ना तो उनको थोड़ा सा वेरियन टाइप का नेचर हो गया झगड़ा वग वो ऐसा नहीं है इनफैक्ट आप गीर में दो बार गया तीसरी बार मैं नहीं गया मतलब अब लायन हो नजरों से गिर गया नजरों से गिर गया गीर तो लायंस बैठे हैं जिप नहीं आ रही आ डंड से हट हट हट हट गाड़ी जाने दो मजा ही नहीं आ रहा सबसे ज्यादा लिपट जो आप कह रहे हैं गुलदार वो गीर में है अच्छा अच्छी बात यह है कि अगर गिर में 300 लेपर्ड की कैपेसिटी 300 लेपर्ड है तो वहां के जो जू है गुजरात में वहां 800 से ज्यादा लेपर्ड सिर्फ उसमें जू में भरे पड़े हुए हैं जिनको उठा उठा के मैटर हो ग बढ़ गए बाहर आ गए डाल रहे हैं अरे उनको जंगल में रिलीज करो यार या दूसरे स् तो लायन अपनी ड्यूटी नहीं कर रहा तो लेपर्ड ही करेगा ना लायन भी मारना आदमी को कौन डराए यार जंगल में घूम रहा है मैं देखता हूं छड़ी लेके घूम रहा है बंदा लायन आए हट हट वहां पे एक ट्राइब है मालधारी जो गाय गर गाय का दूध वगैरह काम करते हैं दूध और दही वगैरह का तो उनके गायों को या मवेशियों को जब वो गाय भैस जो भी होती है जब लाइन मार देते हैं तो वो उसको बाकी जगह प जहर डाल देते हैं उस शिकार पे ताकि दोबारा खाए तोल करने आए तो मर जाए ये कॉर्बेट में और बागड़ में बहुत होता है लेकिन वहां ऐसा नहीं होता वह कहते हैं कि भगवान जंगल में हम रहते हैं और जंगल के भगवान लाय और उन्होंने ये करके प्रसाद अपना लिया है तो उसे माफ कर देते हैं उसमें तो खर वैसे गवर्नमेंट कंपनसेशन भी देती कशन देती है बट कितना देती तुम्हें भी पता और हमें भी पता है इजन कर गुजरात के गुजराती लायंस थोड़ी थोड़ी गुजराती बोलने लगे हैं एनिमेशन बड़ा अच्छा बनेगा जयराज भाई जय श्री कृष्णा कृ लाइन मतलब और लाइन में उतना चाम नहीं है या वो गंदे से दिखते हैं टाइगर रॉयल है अच्छा यह सारा कैट फैमिली पेड़ पर चढ़ जाता है क्या सारा लाइन भी चढ़ जाता है ला मतलब अगर फस जाओ तो लाइन टाइगर ने किल किया था और टाइगर क्या होता मस्त में रहता उस तो राजा है खाना ना खाने के बाद सोने में दूर चला गया अच्छा सफाई पसंद ये बहुत होते हैं किल करके मार के छोड़ देगा य नहीं हबक के खाने लगे पहले दिन रेस्ट करे क् इतनी एनर्जी गई है फिर उसका पेट फाड़ के माल मलीदा सब बाहर निकाल करके और उसको मिट्टी से ढकता है ऐसा भी नहीं कि छोड़ देगा और किल को पकड़ के दूर ले आएगा ढकने की वजह ये होती है कि दुर्गंध या सुगंध तो नहीं कहेंगे दुर्गंध से और जानवर अट्रैक्ट ना हो कर के\n"
}