{
  "chunk_id": "s02_e110_c0013",
  "episode_id": "s02_e110",
  "season": 2,
  "episode": 110,
  "part": null,
  "bonus": false,
  "title": "Prahlad Cha के साथ Panchayat Season 4, Allahabad, Israel-Iran, America पर बतरस Teen Taal S2 Ep.110",
  "chunk_index": 13,
  "word_count": 1000,
  "text": "जो चैन है वो बुलेट चैन तक आ गई लोग बुलेट की चैन बेल्ट बनवा के टहलते थे वो बहुत बड़ा इंपैक्टफुल चीज थी वो तो वहां हाथ वाला रखे थे जो फंसा के मार देता था। नकल डस्टर नहीं नहीं वो सब नहीं नहीं चैन चैन वाला डस्टर वाला और उल्टा पीटता था आदमी क्योंकि चैन टूटता नहीं था पिक्चरों में तोड़ दिया था धाए से भाई लोगों ने बेल्ट बनवाई थी आदमी कभी खिसक जाती थी थी भारी होती थी ना कि वही लाया वही बार-बार पकड़े हुए हैं लगा तो लिया उसने अब वो क्या फिसली जा रही थी मोटी होती थी बुलेट की बेल्ट उसने बेल्ट बनवा ली वो बार-बार कह रहा है क्या हुआ अरे कुछ नहीं क्या हुआ तो बोले फटाओ इसको एक नारा चलता था उस समय 20101 के समय याद है ना मार्क्सवाद ना राष्ट्रवाद बस इलाहाबाद बस इलाहाबाद क्योंकि वो इस तरह की विचारधारा थी ना जो वहां सब विचारधाराओं का समूह था और इलाहाबाद यूनिवर्सिटी की विचारधारा ये है कि वो कुछ भी कर सकती है वो तुरंत अभी मार्क्सवादी विचार से स्विच भी कर सकती है तो वो मतलब सभी विचारों के ऊपर इलाहाबाद है इस बात को प्रभावशाली तरीके से कहने के लिए पढ़ाईवढ़ाई का भी थाना पे जो बाहर से लोग आ रहे हैं पढ़ने के लिए आईएस आईपीएस वाले वो एक अच्छा क्राउड था वो वो उसको लीड करता था बहुत लोग आते वो लीड करता था वो कभी प्रॉपर इलाहाबाद के लोग तो थे नहीं रिहाइशी वो बाहर के लोग थे तो उसमें ढेर सारे पढ़ने वाले लोग भी थे लाइब्रेरी लोग जाके बैठते थे हम पर ये सब के बीच में एक चीज थी कि वो एक थे एक मतलब कि आप उनसे कुछ नहीं कह सकते आप चाहे कहीं भी हो जाइए आप एक यूनिवर्सिटी वाले से कुछ करके देखिए बदतमीजी चाहे आप कोई भी हो पूरा एक से था फिर आप खुद कुछ नहीं छूझ सकते वो डिवाइडेड बाय हॉस्टल नहीं था वो ये था भाई एक लड़के को कैसे हो गया तो वो दुनिया वैसे नहीं कहते हैं कि आप उस साइड जाएंगे तो उसमें चाय का रेट भी कम है समोसा का रेट भी कम है ताकि ये भी खा सकें ये भी खा सकें रोटी बनाने वाली का वो है तो वो एकदम कंट्रोल उसमें रखा है और इलाहाबाद शहर जो है यूनिवर्सिटी में आकर के पढ़ने वाले छात्रों के प्रति हम उनसे आतंकित ज्यादा रहता था कि नहीं नहीं कभी उत्साहित रहता था उत्साहित रहता था और मजा आता था व्यापार भी है ना व्यापार भी है। लोग भी क्या है कि वैसा थोड़ी होता था कि वहां आग लगा के लोग टहल रहे हैं। कुछ चीज़ होती तो मजेदार होता था कि आगे हम लोग के बड़े भाई लोग भी थे। कोई पढ़ाता भी था। कोई ये नहीं कहते हैं। हम पर ये था कि जो है मजेदार क्राउड था। क्राउड रहता था। ऑक्सफोर्ड ऑफ द ईस्ट कहा जाता था। मतलब डीबीसी होता था तब डीबीसी। डीबीसी क्या? दाल भात चोखा। हां हां हां। अरे डीबीसी तो हमेशा रहे। आज तक है वो तो। वो एक ही साथ बनाया जाता है। अच्छा प्लस क्या है कि वकील भी है ना। हां। हमारा दोनों साइड है। हां। वो जो वहां छुपता जा रहा है, वकील बनता जा रहा है। आता ही है नहीं कि तुम एलएलबी तो करते ही रहो। वो कन्वर्ट हो के कब पपीता वाली दुनिया में आ जाता है वो कि एक प्लेट पपीता में नमक डाल के कि भाई शॉर्ट शॉर्ट हो गया कि अब उसमें से काफी तो वो एक चीज़ एक साइकिल का पार्ट बना रहता था। कि तैयारी कर रहे थे दो चार साल। हम्म कोई बात नहीं एलएलबी। अब ये वकील है कचहरी कचहरी और इलाहाबाद तो कचहरी के लिए जाना जाता है ना वहां हर नहीं आपको काला कोट पहनाऊं हां आप लगेंगे वकील मैं मैं गया था एलएलबी पांच साल वाला नहीं था चौधरी चरण सिंह में मेरा हुआ था सर हां मेरठ वाले में मेरठ वाले में एक ही दिन मुझसे छूट गया क्या हाथ नहीं मैंने कहा कि नहीं मैं एक दिन गया मैंने कहा कि ये काम नहीं कर पाऊंगा मैं मेरे घर में काफी लोग वकील हैं हम मैं उनको देखता रहता हूं मैंने कहा पापा ये मत कराइए कुछ और करवा दीजिए। एंट्रेंस भी दिया मैंने हो गया था हम वो गया मेरठ गया एंट्रेंस दिया एग्जाम फीस के बाद सब सेट हो गया पर उसके बाद मेरा दिल ही नहीं गया मेरे मामू वकील है काफी घर में बहुत से लोग वकील हैं और मैंने देखा वो तैयार हो के कहते हैं वो जो पपीते वाला क्लास है ना सेब गाजर का एक डिश होती है जो ये खाते रहते हैं है ना दिन के टाइम पे अरे बाप रे बाप तो छोड़ दिए इलाहाबाद के लौंडे बहुत सारे ऐसे आपको शुरू में लग सकता है ना कि अकुड़ू है या कट्टा प्रेमी हिंसक हैं। लेकिन आप उन्हें जानने लगे कुछ महीनों या कुछ वर्षों के बाद तो आप जानेंगे कि यार बहुत नरम दिल भी है। उसी में लड़के वो भी हैं बहुत कि दोस्त के लिए जान दे देंगे। एक लड़की की चिट्ठी पढ़ लिए जो उसको लड़की लिखी थी जाते हुए जुदाई के हिज्र के समय लिखी गई चिट्ठी और फिर तीन दिन खाना नहीं खाए। है ना? वैसे मैंने भी कैरेक्टर देखे हैं कि बहुत हिंसक भी हैं जरूरत पड़ने पे। यूनिवर्सिटी में सीनियर भी ऐसे ही होता है। बहुत गार्डियन की तरह वो सीनियर लोगों का यह होता है कि किसी ने कुछ लिख दिया तो बहुत दिल पे ले लेते हैं। सच ही लिखा होगा। अरे हम एक दोस्त नहीं पर हमको मतलब वो उनका था एक मसला तो उन्होंने चिट्ठी लिख दी मुझे। उस दिन आए नहीं थे कि डियर फैसल आज तो मैं स्टेशन पे इंतजार करूंगा। पंडाल लोगों में झगड़ा हो गया। तुम वहां मिलना। अब भाई ये लिख दिया गया। तो हमने कहा लगता है सीरियल सीधा झगड़ा हो गया। हमने कहा",
  "search_text": "\nTitle: Prahlad Cha के साथ Panchayat Season 4, Allahabad, Israel-Iran, America पर बतरस Teen Taal S2 Ep.110\n\nEpisode ID: s02_e110\n\nContent:\n\nजो चैन है वो बुलेट चैन तक आ गई लोग बुलेट की चैन बेल्ट बनवा के टहलते थे वो बहुत बड़ा इंपैक्टफुल चीज थी वो तो वहां हाथ वाला रखे थे जो फंसा के मार देता था। नकल डस्टर नहीं नहीं वो सब नहीं नहीं चैन चैन वाला डस्टर वाला और उल्टा पीटता था आदमी क्योंकि चैन टूटता नहीं था पिक्चरों में तोड़ दिया था धाए से भाई लोगों ने बेल्ट बनवाई थी आदमी कभी खिसक जाती थी थी भारी होती थी ना कि वही लाया वही बार-बार पकड़े हुए हैं लगा तो लिया उसने अब वो क्या फिसली जा रही थी मोटी होती थी बुलेट की बेल्ट उसने बेल्ट बनवा ली वो बार-बार कह रहा है क्या हुआ अरे कुछ नहीं क्या हुआ तो बोले फटाओ इसको एक नारा चलता था उस समय 20101 के समय याद है ना मार्क्सवाद ना राष्ट्रवाद बस इलाहाबाद बस इलाहाबाद क्योंकि वो इस तरह की विचारधारा थी ना जो वहां सब विचारधाराओं का समूह था और इलाहाबाद यूनिवर्सिटी की विचारधारा ये है कि वो कुछ भी कर सकती है वो तुरंत अभी मार्क्सवादी विचार से स्विच भी कर सकती है तो वो मतलब सभी विचारों के ऊपर इलाहाबाद है इस बात को प्रभावशाली तरीके से कहने के लिए पढ़ाईवढ़ाई का भी थाना पे जो बाहर से लोग आ रहे हैं पढ़ने के लिए आईएस आईपीएस वाले वो एक अच्छा क्राउड था वो वो उसको लीड करता था बहुत लोग आते वो लीड करता था वो कभी प्रॉपर इलाहाबाद के लोग तो थे नहीं रिहाइशी वो बाहर के लोग थे तो उसमें ढेर सारे पढ़ने वाले लोग भी थे लाइब्रेरी लोग जाके बैठते थे हम पर ये सब के बीच में एक चीज थी कि वो एक थे एक मतलब कि आप उनसे कुछ नहीं कह सकते आप चाहे कहीं भी हो जाइए आप एक यूनिवर्सिटी वाले से कुछ करके देखिए बदतमीजी चाहे आप कोई भी हो पूरा एक से था फिर आप खुद कुछ नहीं छूझ सकते वो डिवाइडेड बाय हॉस्टल नहीं था वो ये था भाई एक लड़के को कैसे हो गया तो वो दुनिया वैसे नहीं कहते हैं कि आप उस साइड जाएंगे तो उसमें चाय का रेट भी कम है समोसा का रेट भी कम है ताकि ये भी खा सकें ये भी खा सकें रोटी बनाने वाली का वो है तो वो एकदम कंट्रोल उसमें रखा है और इलाहाबाद शहर जो है यूनिवर्सिटी में आकर के पढ़ने वाले छात्रों के प्रति हम उनसे आतंकित ज्यादा रहता था कि नहीं नहीं कभी उत्साहित रहता था उत्साहित रहता था और मजा आता था व्यापार भी है ना व्यापार भी है। लोग भी क्या है कि वैसा थोड़ी होता था कि वहां आग लगा के लोग टहल रहे हैं। कुछ चीज़ होती तो मजेदार होता था कि आगे हम लोग के बड़े भाई लोग भी थे। कोई पढ़ाता भी था। कोई ये नहीं कहते हैं। हम पर ये था कि जो है मजेदार क्राउड था। क्राउड रहता था। ऑक्सफोर्ड ऑफ द ईस्ट कहा जाता था। मतलब डीबीसी होता था तब डीबीसी। डीबीसी क्या? दाल भात चोखा। हां हां हां। अरे डीबीसी तो हमेशा रहे। आज तक है वो तो। वो एक ही साथ बनाया जाता है। अच्छा प्लस क्या है कि वकील भी है ना। हां। हमारा दोनों साइड है। हां। वो जो वहां छुपता जा रहा है, वकील बनता जा रहा है। आता ही है नहीं कि तुम एलएलबी तो करते ही रहो। वो कन्वर्ट हो के कब पपीता वाली दुनिया में आ जाता है वो कि एक प्लेट पपीता में नमक डाल के कि भाई शॉर्ट शॉर्ट हो गया कि अब उसमें से काफी तो वो एक चीज़ एक साइकिल का पार्ट बना रहता था। कि तैयारी कर रहे थे दो चार साल। हम्म कोई बात नहीं एलएलबी। अब ये वकील है कचहरी कचहरी और इलाहाबाद तो कचहरी के लिए जाना जाता है ना वहां हर नहीं आपको काला कोट पहनाऊं हां आप लगेंगे वकील मैं मैं गया था एलएलबी पांच साल वाला नहीं था चौधरी चरण सिंह में मेरा हुआ था सर हां मेरठ वाले में मेरठ वाले में एक ही दिन मुझसे छूट गया क्या हाथ नहीं मैंने कहा कि नहीं मैं एक दिन गया मैंने कहा कि ये काम नहीं कर पाऊंगा मैं मेरे घर में काफी लोग वकील हैं हम मैं उनको देखता रहता हूं मैंने कहा पापा ये मत कराइए कुछ और करवा दीजिए। एंट्रेंस भी दिया मैंने हो गया था हम वो गया मेरठ गया एंट्रेंस दिया एग्जाम फीस के बाद सब सेट हो गया पर उसके बाद मेरा दिल ही नहीं गया मेरे मामू वकील है काफी घर में बहुत से लोग वकील हैं और मैंने देखा वो तैयार हो के कहते हैं वो जो पपीते वाला क्लास है ना सेब गाजर का एक डिश होती है जो ये खाते रहते हैं है ना दिन के टाइम पे अरे बाप रे बाप तो छोड़ दिए इलाहाबाद के लौंडे बहुत सारे ऐसे आपको शुरू में लग सकता है ना कि अकुड़ू है या कट्टा प्रेमी हिंसक हैं। लेकिन आप उन्हें जानने लगे कुछ महीनों या कुछ वर्षों के बाद तो आप जानेंगे कि यार बहुत नरम दिल भी है। उसी में लड़के वो भी हैं बहुत कि दोस्त के लिए जान दे देंगे। एक लड़की की चिट्ठी पढ़ लिए जो उसको लड़की लिखी थी जाते हुए जुदाई के हिज्र के समय लिखी गई चिट्ठी और फिर तीन दिन खाना नहीं खाए। है ना? वैसे मैंने भी कैरेक्टर देखे हैं कि बहुत हिंसक भी हैं जरूरत पड़ने पे। यूनिवर्सिटी में सीनियर भी ऐसे ही होता है। बहुत गार्डियन की तरह वो सीनियर लोगों का यह होता है कि किसी ने कुछ लिख दिया तो बहुत दिल पे ले लेते हैं। सच ही लिखा होगा। अरे हम एक दोस्त नहीं पर हमको मतलब वो उनका था एक मसला तो उन्होंने चिट्ठी लिख दी मुझे। उस दिन आए नहीं थे कि डियर फैसल आज तो मैं स्टेशन पे इंतजार करूंगा। पंडाल लोगों में झगड़ा हो गया। तुम वहां मिलना। अब भाई ये लिख दिया गया। तो हमने कहा लगता है सीरियल सीधा झगड़ा हो गया। हमने कहा\n"
}