{
  "chunk_id": "s02_e139_c0022",
  "episode_id": "s02_e139",
  "season": 2,
  "episode": 139,
  "part": null,
  "bonus": false,
  "title": "Iran की weirdness, Gig Work की मुसीबत, नहाने के दीवाने और इंडिया का अमरूद काल Teen Taal S2 Ep 139",
  "chunk_index": 22,
  "word_count": 1000,
  "text": "लोगों ने ले जा के जबरदस्ती नहला के उसका वीडियो बना के डाला है क्योंकि वो वैसा रहता था। उस समय वो बहुत हां अंडर दी इन्फ्लुएंस ऑफ चीजें था। हां कांचा जैसे थे 6 तारीख को [हंसी] 6 तारीख को बोल दूं नहीं नहीं हमको याद नहीं लेकिन बोलिए कि एक तो आदमी न्यू ईयर पार्टी जो है पांच दिन बात करता है लोग सब एक तारीख को करते हैं [हंसी] अच्छा छ तारीख याद आ गया ठीक है रहने दो भूल गए रहने दीजिए रहने दूं हां रहने [हंसी] दीजिए ये जो मयूर विहार में एक जगह है जो पार्टीज के लिए मशहूर है एक पहले मॉल हुआ करता था। आई थिंक उसमें उसको दारू माल ही बना दिया। स्टार मॉल जो भी है। तो एक तो वहां की पुलिस दिल्ली की होशियार और ऊपर से महानुभाव जैसे इनके सारे दोस्तों को बुला महा होशियार आठ लोग। ठीक है? पांच गाड़ियां सब आजकल एक तो हर आदमी अपनी-अपनी गाड़ी से आता है। ठीक है? और वहां पुलिस वालों को पता रहता है कि रेस्टोरेंट में जो है ना चल रहा है पार्टी। ढेरधरे जाएंगे। आज आज धरे जाएंगे। तो उन्होंने भी एक पेड़ है वही पार्किंग लॉट में हम पार्किंग लॉट में के किनारे में एक पेड़ है वहां पे अपनी जो है पुलिस वालों की गाड़ी उस छाया में रात में उसके ऊपर एक तो जीनियस लोग ना ये स्ट्रीट लाइट लगाते पेड़ के ऊपर लाइट लगाया है। पेड़ का ऊपरी भाग पूरा रोशन है। पेड़ के नीचे अंधेरा है। और फॉगी मौसम था उस दिन। खानचा आज ले रहे हैं रात के 12:40 में जबकि 11:00 बजे लास्ट आर्डर होता है। ठीक है 12:40 में तो पुलिस वाले जो है दो थे उन्होंने कह लिया मुर्गा तो ये है ग्रेट मुर्गा क्योंकि ये आदमी रेस्टोरेंट के दरवाजे पे ही लगभग अपने पांच जेब थी इनकी जींस में। ठीक है? पांचों को पांचप बार छुआ होगा। पता नहीं क्या ढूंढ रहा था। उन्होंने कहा यह पैसे वाला आदमी है। यह है नहीं पैसे वाला नहीं है। इसको जब चाबी नहीं मिल रही [हंसी] इसको कोई आईडिया नहीं है। ही इज टन तो उन्होंने टारगेट सेट कर लिया। उसके बाद खानचा जो है पैर उठा रहे हैं। जैसे कि 10-10 मन के एक होम। ठीक है? धीरे-धीरे एकदम। लेकिन वायलेंस नहीं है। वहां पे जैसे रेस्टोरेंट से बाहर आओ छोटा सा गलियारा है टाइप का। उसके बाद मेरे हिसाब कितना 6 इंच टाइप का एक नीचे जाना है जमीन पे कांचा उसमें दो बार उतरे हैं। फिर वापस गए उतरने के लिए। पता नहीं क्या इनके [हंसी] दिमाग में चल रहा था कि मुझे परफेक्ट उतरना है। मेरे बारे में कोई देख रहा होगा टाइप का। परफेक्ट उतर तो उतरे तो टेढ़ा होकर उतरे तो फिर पीछे चले गए और फिर जो है ऐसेसे पैर हिला रहे हैं हवा में कि ऐसा रखूंगा आज इस बार स्ट्रेट डाउन परफेक्ट होगा ये खेल पांच सात मिनट से चल रहा है और पुलिस वाले बस इंतजार कर रहे हैं इनके आदिल भाई आदिल नहीं असलम भाई असलम भाई उनके पास Ford एंडेवर है जो गाड़ी है अब इंडिया में नहीं है बहुत बड़ी गाड़ी है वो निकले इनको पीठ में टाइप का किया कि बाय बाय अपना बैठे एंडडीवर निकली निकल गई फिर राजेश सुंदरम [हंसी] ठीक है हां और केके मैं नहीं केके वो दोनों निकले वरना तो वो दोनों इनको हेल्प कर दूं मदद कर दूं तो फ्रेंचाइज लाइक नो मेरे दोस्त नहीं मेरे मेरे दोस्त [हंसी] ठीक है। उन्होंने कहा सबके भाई घर जाना होता है और उनको तो छोड़ना भी था राजेश को केके की गाड़ी थी वरना उसको छोड़ना भी था हम वरना लेट हो जाती वरना लेट हो जाती वो दोनों गए वरना भी निकल गई पीछे से जो हमारे कॉमन रहीस मित्र हैं एक जिनके पास BMW है उन्होंने उनकी पहली लग्जरी गाड़ी है X1 ठीक है वो तो खानचा की स्थिति देख के सबको दया की आदमी क्या कर रहा है ये खानचा पता है क्या कर रहे थे उस टाइम मुझे ही नहीं पता मैं क्या कर रहा था। [हंसी] ह जलाने की कोशिश कर रहे थे। लेकिन इनके हाथ में जलाने वाली वस्तु नहीं थी। जला रहा था मैं। [हंसी] ठीक है। उसने आ के कहा [हंसी] कि मेरे पास है। इन्होंने कहा थैंक यू दोस्त। थैंक यू। जला दी। फिर ये ऐसा इनको लग रहा था कि चल रहे हैं पर ये चल नहीं रहे थे। इनके अलग ही मूड में थे। पुलिस वाले इंतजार कर रहे हैं। यह बंदा अभी पकड़ेंगे तो कानून कुछ नहीं कर सकते ना। ठीक है? गाड़ी में तो फिर फिर जो है अभिजीत है बंगाली अपना फ्रेंड तो अभिजीत और अजीत ये दोनों अपनी इनकी अपनी-अपनी गाड़ियां हैं। तो वो भी अपनी-अपनी गाड़ियों में गए निकल गए। अब पार्किंग लॉट से इस गैंग की सारी गाड़ियां निकल सब लोग अभी भी स्ट्रगल कर रहे हैं। क्या करूंगा क्या करूं? फिर नई ग्रैंड वििटारा के पास गए और [हंसी] उसको खोलने का प्रयास कर रहे हैं। दो बार लुढ़ के भी ठीक है। फाइनली गाड़ी खुली। अंदर गए। गाड़ी इन्होंने स्टार्ट की। पुलिस वाला आ गया। दोनों तरफ से भाई साहब हेलो कट कट कट दुकान जाने गाड़ी खोली तो बोले कहां चले घर जा रहा हूं नोएडा अच्छा क्या नाम है आसिफ खान तो बोला लाइसेंस दो तो खानचा ने इनका गाड़ी में ही रहता है तो खोल के लाइसेंस दिया बोला कि आरसी तो आरसी दिया बोला आ करो ठीक है हुको तो अरे मशीन लाओ रे उसमें एग्जैक्ट पता चलता है ना तो मशीन लाए तो इन्होंने फूंक मारी जोर से मारो पहले ऐसे क्यों थी जोर से मारी तो मशीन में आया नहीं यार इसमें तो रीडिंग नहीं आ रही इन्होंने कहा क्या ढूंढ रहे हो तो वो कहे कि आपने शराब पी रखी है बोले नहीं मैंने नहीं पिए कैसे नहीं तुमने तुमने पी और तुम्हारे पास ड्राइवर भी नहीं है उसने कहा हां मैंने नहीं पिया मैं गाड़ी चला रहा हूं जिन चाय ने पी थी वो निकल",
  "search_text": "\nTitle: Iran की weirdness, Gig Work की मुसीबत, नहाने के दीवाने और इंडिया का अमरूद काल Teen Taal S2 Ep 139\n\nEpisode ID: s02_e139\n\nContent:\n\nलोगों ने ले जा के जबरदस्ती नहला के उसका वीडियो बना के डाला है क्योंकि वो वैसा रहता था। उस समय वो बहुत हां अंडर दी इन्फ्लुएंस ऑफ चीजें था। हां कांचा जैसे थे 6 तारीख को [हंसी] 6 तारीख को बोल दूं नहीं नहीं हमको याद नहीं लेकिन बोलिए कि एक तो आदमी न्यू ईयर पार्टी जो है पांच दिन बात करता है लोग सब एक तारीख को करते हैं [हंसी] अच्छा छ तारीख याद आ गया ठीक है रहने दो भूल गए रहने दीजिए रहने दूं हां रहने [हंसी] दीजिए ये जो मयूर विहार में एक जगह है जो पार्टीज के लिए मशहूर है एक पहले मॉल हुआ करता था। आई थिंक उसमें उसको दारू माल ही बना दिया। स्टार मॉल जो भी है। तो एक तो वहां की पुलिस दिल्ली की होशियार और ऊपर से महानुभाव जैसे इनके सारे दोस्तों को बुला महा होशियार आठ लोग। ठीक है? पांच गाड़ियां सब आजकल एक तो हर आदमी अपनी-अपनी गाड़ी से आता है। ठीक है? और वहां पुलिस वालों को पता रहता है कि रेस्टोरेंट में जो है ना चल रहा है पार्टी। ढेरधरे जाएंगे। आज आज धरे जाएंगे। तो उन्होंने भी एक पेड़ है वही पार्किंग लॉट में हम पार्किंग लॉट में के किनारे में एक पेड़ है वहां पे अपनी जो है पुलिस वालों की गाड़ी उस छाया में रात में उसके ऊपर एक तो जीनियस लोग ना ये स्ट्रीट लाइट लगाते पेड़ के ऊपर लाइट लगाया है। पेड़ का ऊपरी भाग पूरा रोशन है। पेड़ के नीचे अंधेरा है। और फॉगी मौसम था उस दिन। खानचा आज ले रहे हैं रात के 12:40 में जबकि 11:00 बजे लास्ट आर्डर होता है। ठीक है 12:40 में तो पुलिस वाले जो है दो थे उन्होंने कह लिया मुर्गा तो ये है ग्रेट मुर्गा क्योंकि ये आदमी रेस्टोरेंट के दरवाजे पे ही लगभग अपने पांच जेब थी इनकी जींस में। ठीक है? पांचों को पांचप बार छुआ होगा। पता नहीं क्या ढूंढ रहा था। उन्होंने कहा यह पैसे वाला आदमी है। यह है नहीं पैसे वाला नहीं है। इसको जब चाबी नहीं मिल रही [हंसी] इसको कोई आईडिया नहीं है। ही इज टन तो उन्होंने टारगेट सेट कर लिया। उसके बाद खानचा जो है पैर उठा रहे हैं। जैसे कि 10-10 मन के एक होम। ठीक है? धीरे-धीरे एकदम। लेकिन वायलेंस नहीं है। वहां पे जैसे रेस्टोरेंट से बाहर आओ छोटा सा गलियारा है टाइप का। उसके बाद मेरे हिसाब कितना 6 इंच टाइप का एक नीचे जाना है जमीन पे कांचा उसमें दो बार उतरे हैं। फिर वापस गए उतरने के लिए। पता नहीं क्या इनके [हंसी] दिमाग में चल रहा था कि मुझे परफेक्ट उतरना है। मेरे बारे में कोई देख रहा होगा टाइप का। परफेक्ट उतर तो उतरे तो टेढ़ा होकर उतरे तो फिर पीछे चले गए और फिर जो है ऐसेसे पैर हिला रहे हैं हवा में कि ऐसा रखूंगा आज इस बार स्ट्रेट डाउन परफेक्ट होगा ये खेल पांच सात मिनट से चल रहा है और पुलिस वाले बस इंतजार कर रहे हैं इनके आदिल भाई आदिल नहीं असलम भाई असलम भाई उनके पास Ford एंडेवर है जो गाड़ी है अब इंडिया में नहीं है बहुत बड़ी गाड़ी है वो निकले इनको पीठ में टाइप का किया कि बाय बाय अपना बैठे एंडडीवर निकली निकल गई फिर राजेश सुंदरम [हंसी] ठीक है हां और केके मैं नहीं केके वो दोनों निकले वरना तो वो दोनों इनको हेल्प कर दूं मदद कर दूं तो फ्रेंचाइज लाइक नो मेरे दोस्त नहीं मेरे मेरे दोस्त [हंसी] ठीक है। उन्होंने कहा सबके भाई घर जाना होता है और उनको तो छोड़ना भी था राजेश को केके की गाड़ी थी वरना उसको छोड़ना भी था हम वरना लेट हो जाती वरना लेट हो जाती वो दोनों गए वरना भी निकल गई पीछे से जो हमारे कॉमन रहीस मित्र हैं एक जिनके पास BMW है उन्होंने उनकी पहली लग्जरी गाड़ी है X1 ठीक है वो तो खानचा की स्थिति देख के सबको दया की आदमी क्या कर रहा है ये खानचा पता है क्या कर रहे थे उस टाइम मुझे ही नहीं पता मैं क्या कर रहा था। [हंसी] ह जलाने की कोशिश कर रहे थे। लेकिन इनके हाथ में जलाने वाली वस्तु नहीं थी। जला रहा था मैं। [हंसी] ठीक है। उसने आ के कहा [हंसी] कि मेरे पास है। इन्होंने कहा थैंक यू दोस्त। थैंक यू। जला दी। फिर ये ऐसा इनको लग रहा था कि चल रहे हैं पर ये चल नहीं रहे थे। इनके अलग ही मूड में थे। पुलिस वाले इंतजार कर रहे हैं। यह बंदा अभी पकड़ेंगे तो कानून कुछ नहीं कर सकते ना। ठीक है? गाड़ी में तो फिर फिर जो है अभिजीत है बंगाली अपना फ्रेंड तो अभिजीत और अजीत ये दोनों अपनी इनकी अपनी-अपनी गाड़ियां हैं। तो वो भी अपनी-अपनी गाड़ियों में गए निकल गए। अब पार्किंग लॉट से इस गैंग की सारी गाड़ियां निकल सब लोग अभी भी स्ट्रगल कर रहे हैं। क्या करूंगा क्या करूं? फिर नई ग्रैंड वििटारा के पास गए और [हंसी] उसको खोलने का प्रयास कर रहे हैं। दो बार लुढ़ के भी ठीक है। फाइनली गाड़ी खुली। अंदर गए। गाड़ी इन्होंने स्टार्ट की। पुलिस वाला आ गया। दोनों तरफ से भाई साहब हेलो कट कट कट दुकान जाने गाड़ी खोली तो बोले कहां चले घर जा रहा हूं नोएडा अच्छा क्या नाम है आसिफ खान तो बोला लाइसेंस दो तो खानचा ने इनका गाड़ी में ही रहता है तो खोल के लाइसेंस दिया बोला कि आरसी तो आरसी दिया बोला आ करो ठीक है हुको तो अरे मशीन लाओ रे उसमें एग्जैक्ट पता चलता है ना तो मशीन लाए तो इन्होंने फूंक मारी जोर से मारो पहले ऐसे क्यों थी जोर से मारी तो मशीन में आया नहीं यार इसमें तो रीडिंग नहीं आ रही इन्होंने कहा क्या ढूंढ रहे हो तो वो कहे कि आपने शराब पी रखी है बोले नहीं मैंने नहीं पिए कैसे नहीं तुमने तुमने पी और तुम्हारे पास ड्राइवर भी नहीं है उसने कहा हां मैंने नहीं पिया मैं गाड़ी चला रहा हूं जिन चाय ने पी थी वो निकल\n"
}