{
  "chunk_id": "s02_e107_c0016",
  "episode_id": "s02_e107",
  "season": 2,
  "episode": 107,
  "part": null,
  "bonus": false,
  "title": "Ukraine का Russia पर Drone Strike, RCB Victory Tragedy और Hilarious Salad Talk Teen Taal S2 Ep 107",
  "chunk_index": 16,
  "word_count": 1000,
  "text": "नहीं फिर खीरा बोलता नहीं है ना। नहीं नहीं वो सलाद में जाएगा ना। अच्छा वो तो मटन के इंतजार में रहे होंगे ना। बाकी लोग हां बाकी लोग जिन्होंने एक बकरे की बलि दी है। उसका भी तो कुछ बनेगा ना। तो खीरे का भी बन जाता है। पर प्रसाद मानते हैं दोनों को। हम प्रसाद की श्रेणी में दोनों आते हैं। हम और दोनों साथ में खाए ना नहीं कह सकते आप कि आप किसी के घर के दरवाजे से गुजर रहे हैं और उन्होंने कहा कि आओ बेटा थोड़ा प्रसाद ले लो हम तो आप मिठाई की अपेक्षा ना करें नवमी का दिन है आप जाएंगे आपको भर के उस दिन खिलाया जाएगा तो वो मतलब सब सब जगह नहीं होता हमारे इधर पूर्व में होता है क्योंकि इधर उतनी रोशनी पहुंची नहीं है आपने बताया था उस दिन कि उस दिन अगर घर से निकलो तो पकड़ पकड़ के खिला हां उस दिन बहुत खा लेता है क्योंकि अब म आदमी का पेट तो उतना ही बड़ा है ना नवमी है तो क्या हुआ लेकिन उसके घर में ज्यादा बना हुआ है अब सब नहीं सब अरे बाजार से लाते हैं तो 1 किलो 2 किलो लाते हैं ना पर उस दिन तो आपका कंट्रोल नहीं है ना बिल्कुल घर में ही तो बना 5 किलो का है 4 किलो का है वो तो जो भी है तो आपने बलि तो दे दी अब उसको सिम्टम और बन भी रहा है और प्रसाद जो है बनने के बाद ही दे सकते हैं तो बन जाने के बाद कोई गुजर रहा है तो वह लोग भी ताड़ते रहते हैं कि कोई गुजर जाए हम हम है ना गांव में फ्रिज नहीं होता बिलकुल रात तक खराब हो संभावना नहीं अगले दिन तक चल जाता है पर संभव पर बहुत ज्यादा माल है ना हम बहुत ज्यादा है तो फिर उस दिन आप प्याज भी खा सकते हैं खीरा वैसे भी राइम भी करता है काफिया भी मिलता है उन चीजों से जिसका हमारे मिडिल क्लास को ऑब्सेशन है हीरा हम या संभवत जीरा भी हम मतलब जो हीरा अगर सुबह खाएं तो बहुत फायदेमंद है। कहावत है हम सुबह का खीरा खीरा खीरा दोपहर का खीरा पीड़ा खीरा हम रात का खीरा रात का खीरा पीड़ा कहावत है साइंटिफिकली बैक्ड नहीं है ये ध्यान रखिए पर अगर आप ऐसे जो लोक विज़डम है हम फोक विज़डम है हम उसमें यकीन रखते हैं तो ये एक सिग्नल होता था कि खीरा सुबह खाओगे तो सबसे फायदेमंद है। हम दोपहर का खीरा खीरा ही है। हम नथिंग स्पेशल अबाउट इट लेकिन शाम का खीरा हम नॉट गुड फॉर यू उस टाइप का हो जाता है हां वो वाला हो जाता है तो शाम का खीरा पीड़ा जो शाम में बहुत सारी चीजें वर्जित होती है ना दही नहीं मूली मूली नहीं खीरे में भी होता है आपकी आपका जो कफ है हम कफ पित्त और वात तीन तरह की चीजें होती हैं। तो रहता है कि वो कफ को बढ़ाएगा अगर आप रात में वो बेसिकली मुझे लगता है सर्दियों के लिए कहा गया होगा गर्मियों में नहीं खीरा गर्मियों में होता है जनरली नहीं अब तो 12 महीने मिलता है हां वो पर कहावत जब लिखी गई होगी तब 12 महीने नहीं होगा और सीजन के अलावा खाना भी नहीं चाहिए खीरा हम कोई भी चीज सीजन के बाहर मत खाइए अब तो पता ही नहीं चलता किसका सीजन आया है गोभी का सीजन है कि बैंगन का सब चीज उपलब्ध है चमकता हुआ खीरा का सबसे बड़ा अह उपलब्धि जो मैंने देखा था वो वो कृष्ण जन्माष्टमी जब आती है तो चना जो होता है वो खीरे में पिरो दिया जाता है। घुसा देते हैं। फिर दूसरे दिन वो फूट हल्का सा फटता है और ये हम मान लेते हैं कृष्ण जी का जन्म हो गया। हम तो वो भी खीरे से ही होता है। राधे-राधे राधे-राधे। खीरा एक ऐसी चीज होती थी कि अगर आप खेत से गुजर रहे हैं। दिखने में अच्छा लग गया। हम जीभ लपलपा गई तो तोड़ लीजिए। और मुहाने तो आधा वही पानी में नगर में ट्यूटी लगी है धो लीजिए और मुंडी काटिए मुंह से थूक दीजिए थूक दीजिए और खा लीजिए धोना भी नहीं होता था यार नो कोई भी नहीं और उसका टेस्ट ओ मैं ये मानता हूं साइंटिफिकली पता नहीं कैसे प्रूव होगा पर तोड़ने के तुरंत बाद अगर खाएंगे तो उसका टेस्ट अलग होता है। घर पहुंचने के बाद टेस्ट अलग होता है और अगले दिन तो खीर खीरे की चमड़ी सिकुड़ सी जाती है। और वो दूसरे दिन शाम तक रह गया तो झूल झुर्रियां हो जाती है उसके उसके अंदर फिर वो मेहमानों को खिला दिया जाता है। हां जहां फ्रिज नहीं होता था ऐसे ज्यादा रख देंगे सर खीरे से बनने वाली अलग-अलग डिशेस में मुझे वो बहुत पसंद है। कुकंबर और हंग कर्ड का डीप। अरे बाप रे नहीं अंग्रेजी बोल रहे हो तुम। हां दही दही दही और खीरे का डीप जो है वो बढ़िया इसमें थोड़ा लहसुनिया फ्लेवर भी पड़ता है चाट मसाला वगैरह डाल दो बढ़िया मसाला वसाला नहीं हम और एक खीरे की वो भी बनती है कूटने कूट कर कूचा हुआ कूचा छीलने के बाद उसको कूट दीजिए और फिर उसमें पेपर ब्लैक पेपर डाल के वो भी बढ़िया लगता है सैंडविच रायता में तो खैर डलता ही है वो तो मैं कभी-कभी खीरा भर के ना फ्रेश अगर खीरा होता है। सादा ब्रेड मतलब सेका हुआ ना हो कच्चा ब्रेड कच्चा खीरा हल्का सा बढ़िया रहता है। कच कच कच कच मजा आ जाता है। क्रिस्पी रहता है। लेकिन सैंडविच में जो खीरा डाल के गरम करते हैं ना खीरा की ऐसी तैसी मार देते हैं। हां लीजिहा हो जाता है। मतलब उसको करने का तरीका ये है सब अब जैसे मैं बनाता हूं तो आप अपना ब्रेड को काटिए। उसमें जो भी आपको लगाना है अपनी सुविधा अनुसार बटर लगाना है या चीज लगाना है तो उसको करके फिर उसको हल्का गम कर लीजिए। फिर",
  "search_text": "\nTitle: Ukraine का Russia पर Drone Strike, RCB Victory Tragedy और Hilarious Salad Talk Teen Taal S2 Ep 107\n\nEpisode ID: s02_e107\n\nContent:\n\nनहीं फिर खीरा बोलता नहीं है ना। नहीं नहीं वो सलाद में जाएगा ना। अच्छा वो तो मटन के इंतजार में रहे होंगे ना। बाकी लोग हां बाकी लोग जिन्होंने एक बकरे की बलि दी है। उसका भी तो कुछ बनेगा ना। तो खीरे का भी बन जाता है। पर प्रसाद मानते हैं दोनों को। हम प्रसाद की श्रेणी में दोनों आते हैं। हम और दोनों साथ में खाए ना नहीं कह सकते आप कि आप किसी के घर के दरवाजे से गुजर रहे हैं और उन्होंने कहा कि आओ बेटा थोड़ा प्रसाद ले लो हम तो आप मिठाई की अपेक्षा ना करें नवमी का दिन है आप जाएंगे आपको भर के उस दिन खिलाया जाएगा तो वो मतलब सब सब जगह नहीं होता हमारे इधर पूर्व में होता है क्योंकि इधर उतनी रोशनी पहुंची नहीं है आपने बताया था उस दिन कि उस दिन अगर घर से निकलो तो पकड़ पकड़ के खिला हां उस दिन बहुत खा लेता है क्योंकि अब म आदमी का पेट तो उतना ही बड़ा है ना नवमी है तो क्या हुआ लेकिन उसके घर में ज्यादा बना हुआ है अब सब नहीं सब अरे बाजार से लाते हैं तो 1 किलो 2 किलो लाते हैं ना पर उस दिन तो आपका कंट्रोल नहीं है ना बिल्कुल घर में ही तो बना 5 किलो का है 4 किलो का है वो तो जो भी है तो आपने बलि तो दे दी अब उसको सिम्टम और बन भी रहा है और प्रसाद जो है बनने के बाद ही दे सकते हैं तो बन जाने के बाद कोई गुजर रहा है तो वह लोग भी ताड़ते रहते हैं कि कोई गुजर जाए हम हम है ना गांव में फ्रिज नहीं होता बिलकुल रात तक खराब हो संभावना नहीं अगले दिन तक चल जाता है पर संभव पर बहुत ज्यादा माल है ना हम बहुत ज्यादा है तो फिर उस दिन आप प्याज भी खा सकते हैं खीरा वैसे भी राइम भी करता है काफिया भी मिलता है उन चीजों से जिसका हमारे मिडिल क्लास को ऑब्सेशन है हीरा हम या संभवत जीरा भी हम मतलब जो हीरा अगर सुबह खाएं तो बहुत फायदेमंद है। कहावत है हम सुबह का खीरा खीरा खीरा दोपहर का खीरा पीड़ा खीरा हम रात का खीरा रात का खीरा पीड़ा कहावत है साइंटिफिकली बैक्ड नहीं है ये ध्यान रखिए पर अगर आप ऐसे जो लोक विज़डम है हम फोक विज़डम है हम उसमें यकीन रखते हैं तो ये एक सिग्नल होता था कि खीरा सुबह खाओगे तो सबसे फायदेमंद है। हम दोपहर का खीरा खीरा ही है। हम नथिंग स्पेशल अबाउट इट लेकिन शाम का खीरा हम नॉट गुड फॉर यू उस टाइप का हो जाता है हां वो वाला हो जाता है तो शाम का खीरा पीड़ा जो शाम में बहुत सारी चीजें वर्जित होती है ना दही नहीं मूली मूली नहीं खीरे में भी होता है आपकी आपका जो कफ है हम कफ पित्त और वात तीन तरह की चीजें होती हैं। तो रहता है कि वो कफ को बढ़ाएगा अगर आप रात में वो बेसिकली मुझे लगता है सर्दियों के लिए कहा गया होगा गर्मियों में नहीं खीरा गर्मियों में होता है जनरली नहीं अब तो 12 महीने मिलता है हां वो पर कहावत जब लिखी गई होगी तब 12 महीने नहीं होगा और सीजन के अलावा खाना भी नहीं चाहिए खीरा हम कोई भी चीज सीजन के बाहर मत खाइए अब तो पता ही नहीं चलता किसका सीजन आया है गोभी का सीजन है कि बैंगन का सब चीज उपलब्ध है चमकता हुआ खीरा का सबसे बड़ा अह उपलब्धि जो मैंने देखा था वो वो कृष्ण जन्माष्टमी जब आती है तो चना जो होता है वो खीरे में पिरो दिया जाता है। घुसा देते हैं। फिर दूसरे दिन वो फूट हल्का सा फटता है और ये हम मान लेते हैं कृष्ण जी का जन्म हो गया। हम तो वो भी खीरे से ही होता है। राधे-राधे राधे-राधे। खीरा एक ऐसी चीज होती थी कि अगर आप खेत से गुजर रहे हैं। दिखने में अच्छा लग गया। हम जीभ लपलपा गई तो तोड़ लीजिए। और मुहाने तो आधा वही पानी में नगर में ट्यूटी लगी है धो लीजिए और मुंडी काटिए मुंह से थूक दीजिए थूक दीजिए और खा लीजिए धोना भी नहीं होता था यार नो कोई भी नहीं और उसका टेस्ट ओ मैं ये मानता हूं साइंटिफिकली पता नहीं कैसे प्रूव होगा पर तोड़ने के तुरंत बाद अगर खाएंगे तो उसका टेस्ट अलग होता है। घर पहुंचने के बाद टेस्ट अलग होता है और अगले दिन तो खीर खीरे की चमड़ी सिकुड़ सी जाती है। और वो दूसरे दिन शाम तक रह गया तो झूल झुर्रियां हो जाती है उसके उसके अंदर फिर वो मेहमानों को खिला दिया जाता है। हां जहां फ्रिज नहीं होता था ऐसे ज्यादा रख देंगे सर खीरे से बनने वाली अलग-अलग डिशेस में मुझे वो बहुत पसंद है। कुकंबर और हंग कर्ड का डीप। अरे बाप रे नहीं अंग्रेजी बोल रहे हो तुम। हां दही दही दही और खीरे का डीप जो है वो बढ़िया इसमें थोड़ा लहसुनिया फ्लेवर भी पड़ता है चाट मसाला वगैरह डाल दो बढ़िया मसाला वसाला नहीं हम और एक खीरे की वो भी बनती है कूटने कूट कर कूचा हुआ कूचा छीलने के बाद उसको कूट दीजिए और फिर उसमें पेपर ब्लैक पेपर डाल के वो भी बढ़िया लगता है सैंडविच रायता में तो खैर डलता ही है वो तो मैं कभी-कभी खीरा भर के ना फ्रेश अगर खीरा होता है। सादा ब्रेड मतलब सेका हुआ ना हो कच्चा ब्रेड कच्चा खीरा हल्का सा बढ़िया रहता है। कच कच कच कच मजा आ जाता है। क्रिस्पी रहता है। लेकिन सैंडविच में जो खीरा डाल के गरम करते हैं ना खीरा की ऐसी तैसी मार देते हैं। हां लीजिहा हो जाता है। मतलब उसको करने का तरीका ये है सब अब जैसे मैं बनाता हूं तो आप अपना ब्रेड को काटिए। उसमें जो भी आपको लगाना है अपनी सुविधा अनुसार बटर लगाना है या चीज लगाना है तो उसको करके फिर उसको हल्का गम कर लीजिए। फिर\n"
}